{"status":"OK","subtests":[{"name":"Must not throw INVALID_STATE_ERR for a detached node.","status":"PASS"},{"name":"Must throw TypeError when calling without arguments","status":"PASS"},{"name":"Simple test with paragraphs","status":"PASS"},{"name":"Don't auto-create <body> when applied to <html>","status":"PASS"},{"name":"<script>s should be run when appended to the document (but not before)","status":"PASS"},{"name":"createContextualFragment should work even when the context is <area>","status":"PASS"},{"name":"createContextualFragment should work even when the context is <base>","status":"PASS"},{"name":"createContextualFragment should work even when the context is <basefont>","status":"PASS"},{"name":"createContextualFragment should work even when the context is <bgsound>","status":"PASS"},{"name":"createContextualFragment should work even when the context is <br>","status":"PASS"},{"name":"createContextualFragment should work even when the context is <col>","status":"PASS"},{"name":"createContextualFragment should work even when the context is <embed>","status":"PASS"},{"name":"createContextualFragment should work even when the context is <frame>","status":"PASS"},{"name":"createContextualFragment should work even when the context is <hr>","status":"PASS"},{"name":"createContextualFragment should work even when the context is <img>","status":"PASS"},{"name":"createContextualFragment should work even when the context is <input>","status":"PASS"},{"name":"createContextualFragment should work even when the context is <keygen>","status":"PASS"},{"name":"createContextualFragment should work even when the context is <link>","status":"PASS"},{"name":"createContextualFragment should work even when the context is <meta>","status":"PASS"},{"name":"createContextualFragment should work even when the context is <param>","status":"PASS"},{"name":"createContextualFragment should work even when the context is <source>","status":"PASS"},{"name":"createContextualFragment should work even when the context is <track>","status":"PASS"},{"name":"createContextualFragment should work even when the context is <wbr>","status":"PASS"},{"name":"createContextualFragment should work even when the context is <menuitem>","status":"PASS"},{"name":"createContextualFragment should work even when the context is <image>","status":"PASS"},{"name":"<html> and <body> must work the same, 1","status":"PASS"},{"name":"<html> and <body> must work the same, 2","status":"PASS"},{"name":"Implicit <body> creation","status":"PASS"},{"name":"Namespace generally shouldn't matter","status":"PASS"},{"name":"<html> in a different namespace shouldn't be special","status":"PASS"},{"name":"SVG namespace shouldn't be special","status":"FAIL"},{"name":"null should be stringified","status":"PASS"},{"name":"undefined should be stringified","status":"PASS"},{"name":"Text nodes shouldn't be special","status":"PASS"},{"name":"Non-Element parent should not be special","status":"PASS"}]}