{"status":"OK","subtests":[{"name":"Anchor element with target=_blank with rel=noopener","status":"FAIL"},{"name":"Anchor element with target=_blank with rel=opener","status":"FAIL"},{"name":"Anchor element with target=_blank with implicit rel=noopener","status":"FAIL"},{"name":"Anchor element with target=_blank with rel=opener+noopener","status":"FAIL"},{"name":"Anchor element with target=_blank with rel=noopener+opener","status":"FAIL"},{"name":"Anchor element with target=_blank with rel=noreferrer","status":"FAIL"},{"name":"Anchor element with target=_blank with rel=opener+noreferrer","status":"FAIL"},{"name":"Anchor element with target=_blank with rel=noopener+opener+noreferrer","status":"FAIL"},{"name":"Area element with target=_blank with rel=noopener","status":"FAIL"},{"name":"Area element with target=_blank with rel=opener","status":"FAIL"},{"name":"Area element with target=_blank with implicit rel=noopener","status":"FAIL"},{"name":"Area element with target=_blank with rel=opener+noopener","status":"FAIL"},{"name":"Area element with target=_blank with rel=noopener+opener","status":"FAIL"}]}