{"status":"OK","subtests":[{"name":"Focus should not be restored if the currently focused element is not inside the dialog.","status":"PASS"},{"name":"Focus restore should not occur when the focused element is in a shadowroot outside of the dialog.","status":"PASS"},{"name":"Focus restore should occur when the focused element is in a shadowroot inside the dialog.","status":"PASS"},{"name":"Focus restore should occur when the focused element is slotted into a dialog.","status":"PASS"},{"name":"Focus restore should always occur for modal dialogs.","status":"PASS"}]}