{"status":"OK","subtests":[{"name":"Offsets for inset-area: span-all","status":"FAIL"},{"name":"Offsets for inset-area: top left","status":"FAIL"},{"name":"Offsets for inset-area: top center","status":"FAIL"},{"name":"Offsets for inset-area: top right","status":"FAIL"},{"name":"Offsets for inset-area: center left","status":"FAIL"},{"name":"Offsets for inset-area: center center","status":"FAIL"},{"name":"Offsets for inset-area: center right","status":"FAIL"},{"name":"Offsets for inset-area: bottom left","status":"FAIL"},{"name":"Offsets for inset-area: bottom center","status":"FAIL"},{"name":"Offsets for inset-area: bottom right","status":"FAIL"},{"name":"Offsets for inset-area: top span-left","status":"FAIL"},{"name":"Offsets for inset-area: top span-right","status":"FAIL"},{"name":"Offsets for inset-area: span-top left","status":"FAIL"},{"name":"Offsets for inset-area: span-bottom left","status":"FAIL"}]}