{"status":"ERROR","subtests":[{"name":"@scope (.a) is valid","status":"FAIL"},{"name":"@scope (.a + .b) is valid","status":"NOTRUN"},{"name":"@scope (.a:hover) is valid","status":"NOTRUN"},{"name":"@scope (.a:hover, #b, div) is valid","status":"NOTRUN"},{"name":"@scope (:is(div, span)) is valid","status":"NOTRUN"},{"name":"@scope (.a) to (.b) is valid","status":"NOTRUN"},{"name":"@scope (.a)to (.b) is valid","status":"NOTRUN"},{"name":"@scope (.a) to (.b:hover, #c, div) is valid","status":"NOTRUN"},{"name":"@scope is valid","status":"NOTRUN"},{"name":"@scope (.a) to (&) is valid","status":"NOTRUN"},{"name":"@scope (.a) to (& > &) is valid","status":"NOTRUN"},{"name":"@scope (.a) to (> .b) is valid","status":"NOTRUN"},{"name":"@scope (.a) to (+ .b) is valid","status":"NOTRUN"},{"name":"@scope (.a) to (~ .b) is valid","status":"NOTRUN"},{"name":"@scope (.c <> .d) is valid","status":"NOTRUN"},{"name":"@scope (.a, .c <> .d) is valid","status":"NOTRUN"},{"name":"@scope (.a <> .b, .c) is valid","status":"NOTRUN"},{"name":"@scope (div::before) is valid","status":"NOTRUN"},{"name":"@scope (div::after) is valid","status":"NOTRUN"},{"name":"@scope (slotted(div)) is valid","status":"NOTRUN"},{"name":"@scope (.a) to (div::before) is valid","status":"NOTRUN"},{"name":"@scope (.a) unknown (.c) is not valid","status":"NOTRUN"},{"name":"@scope (.a) to unknown (.c) is not valid","status":"NOTRUN"},{"name":"@scope (.a) 1px (.c) is not valid","status":"NOTRUN"},{"name":"@scope (.a) to unknown(c) is not valid","status":"NOTRUN"},{"name":"@scope unknown(.a) is not valid","status":"NOTRUN"},{"name":"@scope 1px is not valid","status":"NOTRUN"},{"name":"@scope creep is not valid","status":"NOTRUN"}]}