{"status":"ERROR","subtests":[{"name":"cast float32 0D tensor to int32 / async","status":"NOTRUN"},{"name":"cast float32 1D tensor to int32 / async","status":"NOTRUN"},{"name":"cast float32 2D tensor to int32 / async","status":"NOTRUN"},{"name":"cast float32 3D tensor to int32 / async","status":"NOTRUN"},{"name":"cast float32 4D tensor to int32 / async","status":"NOTRUN"},{"name":"cast float32 5D tensor to int32 / async","status":"NOTRUN"},{"name":"cast float32 4D tensor to float16 / async","status":"NOTRUN"},{"name":"cast float32 4D tensor to uint32 / async","status":"NOTRUN"},{"name":"cast float32 4D tensor to int64 / async","status":"NOTRUN"},{"name":"cast float32 4D tensor to int8 / async","status":"NOTRUN"},{"name":"cast float32 4D tensor to uint8 / async","status":"NOTRUN"},{"name":"cast float16 4D tensor to float32 / async","status":"NOTRUN"},{"name":"cast float16 4D tensor to int32 / async","status":"NOTRUN"},{"name":"cast float16 4D tensor to uint32 / async","status":"NOTRUN"},{"name":"cast float16 4D tensor to int64 / async","status":"NOTRUN"},{"name":"cast float16 4D tensor to int8 / async","status":"NOTRUN"},{"name":"cast float16 4D tensor to uint8 / async","status":"NOTRUN"},{"name":"cast int32 4D tensor to float32 / async","status":"NOTRUN"},{"name":"cast int32 4D tensor to float16 / async","status":"NOTRUN"},{"name":"cast int32 4D tensor to int64 / async","status":"NOTRUN"},{"name":"cast int32 4D tensor to int8 / async","status":"NOTRUN"},{"name":"cast int32 4D tensor to uint8 / async","status":"NOTRUN"},{"name":"cast uint32 4D tensor to float32 / async","status":"NOTRUN"},{"name":"cast uint32 4D tensor to float16 / async","status":"NOTRUN"},{"name":"cast uint32 4D tensor to int32 / async","status":"NOTRUN"},{"name":"cast uint32 4D tensor to int64 / async","status":"NOTRUN"},{"name":"cast uint32 4D tensor to int8 / async","status":"NOTRUN"},{"name":"cast uint32 4D tensor to uint8 / async","status":"NOTRUN"},{"name":"cast int64 4D tensor to float32 / async","status":"NOTRUN"},{"name":"cast int64 4D tensor to float16 / async","status":"NOTRUN"},{"name":"cast int64 4D tensor to int32 / async","status":"NOTRUN"},{"name":"cast int64 4D tensor to uint32 / async","status":"NOTRUN"},{"name":"cast int64 4D tensor to int8 / async","status":"NOTRUN"},{"name":"cast int64 4D tensor to uint8 / async","status":"NOTRUN"},{"name":"cast int8 4D tensor to float32 / async","status":"NOTRUN"},{"name":"cast int8 4D tensor to float16 / async","status":"NOTRUN"},{"name":"cast int8 4D tensor to int32 / async","status":"NOTRUN"},{"name":"cast int8 4D tensor to uint32 / async","status":"NOTRUN"},{"name":"cast int8 4D tensor to int64 / async","status":"NOTRUN"},{"name":"cast int8 4D tensor to uint8 / async","status":"NOTRUN"},{"name":"cast uint8 4D tensor to float32 / async","status":"NOTRUN"},{"name":"cast uint8 4D tensor to float16 / async","status":"NOTRUN"},{"name":"cast uint8 4D tensor to int32 / async","status":"NOTRUN"},{"name":"cast uint8 4D tensor to uint32 / async","status":"NOTRUN"},{"name":"cast uint8 4D tensor to int64 / async","status":"NOTRUN"},{"name":"cast uint8 4D tensor to int8 / async","status":"NOTRUN"}]}