{"status":"OK","subtests":[{"name":"'no crossorigin attribute' should send a credential to a same origin bundle","status":"FAIL"},{"name":"'no crossorigin attribute' should send a credential to a cross origin bundle","status":"FAIL"},{"name":"'anonymous' should send a credential to a same origin bundle","status":"FAIL"},{"name":"'anonymous' should not send a credential to a cross origin bundle","status":"PASS"},{"name":"'use-credentials' should send a credential to a same origin bundle","status":"FAIL"},{"name":"'use-credentials' should send a credential to a cross origin bundle","status":"FAIL"}]}