{"status":"OK","subtests":[{"name":"bottom responsive to style changes","status":"FAIL"},{"name":"height responsive to style changes","status":"FAIL"},{"name":"letterSpacing responsive to style changes","status":"FAIL"},{"name":"letterSpacing can be normal","status":"FAIL"},{"name":"marginRight responsive to style changes","status":"FAIL"},{"name":"marginRight allows percentages","status":"FAIL"},{"name":"outlineOffset responsive to style changes","status":"FAIL"},{"name":"perspective responsive to style changes","status":"FAIL"},{"name":"perspective can be none","status":"FAIL"},{"name":"wordSpacing responsive to style changes","status":"FAIL"}]}