{"status":"OK","subtests":[{"name":"cancelling the readable side should call transformer.cancel()","status":"PASS"},{"name":"cancelling the readable side should reject if transformer.cancel() throws","status":"PASS"},{"name":"aborting the writable side should call transformer.abort()","status":"PASS"},{"name":"aborting the writable side should reject if transformer.cancel() throws","status":"PASS"},{"name":"closing the writable side should reject if a parallel transformer.cancel() throws","status":"PASS"},{"name":"readable.cancel() and a parallel writable.close() should reject if a transformer.cancel() calls controller.error()","status":"PASS"},{"name":"writable.abort() and readable.cancel() should reject if a transformer.cancel() calls controller.error()","status":"PASS"}]}