{"status":"OK","subtests":[{"name":"Can set 'overflow-wrap' to CSS-wide keywords","status":"PASS"},{"name":"Can set 'overflow-wrap' to var() references","status":"PASS"},{"name":"Can set 'overflow-wrap' to the 'normal' keyword","status":"PASS"},{"name":"Can set 'overflow-wrap' to the 'break-word' keyword","status":"PASS"},{"name":"Can set 'overflow-wrap' to the 'break-spaces' keyword","status":"FAIL"},{"name":"Setting 'overflow-wrap' to a length throws TypeError","status":"PASS"},{"name":"Setting 'overflow-wrap' to a percent throws TypeError","status":"PASS"},{"name":"Setting 'overflow-wrap' to a time throws TypeError","status":"PASS"},{"name":"Setting 'overflow-wrap' to an angle throws TypeError","status":"PASS"},{"name":"Setting 'overflow-wrap' to a flexible length throws TypeError","status":"PASS"},{"name":"Setting 'overflow-wrap' to a number throws TypeError","status":"PASS"},{"name":"Setting 'overflow-wrap' to a position throws TypeError","status":"PASS"},{"name":"Setting 'overflow-wrap' to a URL throws TypeError","status":"PASS"},{"name":"Setting 'overflow-wrap' to a transform throws TypeError","status":"PASS"},{"name":"'overflow-wrap' does not supported 'break-overflow break-spaces'","status":"FAIL"}]}