{"status":"OK","subtests":[{"name":"sending a plain empty object","status":"PASS"},{"name":"sending the ES Math object","status":"PASS"},{"name":"sending a new XHR instance","status":"PASS"},{"name":"sending object that stringifies to undefined","status":"PASS"},{"name":"sending object that stringifies to null","status":"PASS"},{"name":"object that stringifies to query string","status":"PASS"},{"name":"object that stringifies to JSON string","status":"PASS"},{"name":"object whose valueOf() returns a document - ignore valueOf(), stringify","status":"PASS"},{"name":"object whose toString() returns a document, expected to throw","status":"PASS"},{"name":"object whose toString() throws, expected to throw","status":"PASS"}]}