{"status":"OK","subtests":[{"name":"idl_test setup","status":"PASS"},{"name":"idl_test validation","status":"PASS"},{"name":"ResizeObserverEntry creator","status":"PASS"},{"name":"Element includes ParentNode: member names are unique","status":"PASS"},{"name":"Element includes NonDocumentTypeChildNode: member names are unique","status":"PASS"},{"name":"Element includes ChildNode: member names are unique","status":"PASS"},{"name":"Element includes Slotable: member names are unique","status":"PASS"},{"name":"ResizeObserver interface: existence and properties of interface object","status":"PASS"},{"name":"ResizeObserver interface object length","status":"PASS"},{"name":"ResizeObserver interface object name","status":"PASS"},{"name":"ResizeObserver interface: existence and properties of interface prototype object","status":"PASS"},{"name":"ResizeObserver interface: existence and properties of interface prototype object's \"constructor\" property","status":"PASS"},{"name":"ResizeObserver interface: existence and properties of interface prototype object's @@unscopables property","status":"PASS"},{"name":"ResizeObserver interface: operation observe(Element, ResizeObserverOptions)","status":"PASS"},{"name":"ResizeObserver interface: operation unobserve(Element)","status":"PASS"},{"name":"ResizeObserver interface: operation disconnect()","status":"PASS"},{"name":"ResizeObserver must be primary interface of observer","status":"PASS"},{"name":"Stringification of observer","status":"PASS"},{"name":"ResizeObserver interface: observer must inherit property \"observe(Element, ResizeObserverOptions)\" with the proper type","status":"PASS"},{"name":"ResizeObserver interface: calling observe(Element, ResizeObserverOptions) on observer with too few arguments must throw TypeError","status":"PASS"},{"name":"ResizeObserver interface: observer must inherit property \"unobserve(Element)\" with the proper type","status":"PASS"},{"name":"ResizeObserver interface: calling unobserve(Element) on observer with too few arguments must throw TypeError","status":"PASS"},{"name":"ResizeObserver interface: observer must inherit property \"disconnect()\" with the proper type","status":"PASS"},{"name":"ResizeObserverEntry interface: existence and properties of interface object","status":"PASS"},{"name":"ResizeObserverEntry interface object length","status":"FAIL"},{"name":"ResizeObserverEntry interface object name","status":"PASS"},{"name":"ResizeObserverEntry interface: existence and properties of interface prototype object","status":"PASS"},{"name":"ResizeObserverEntry interface: existence and properties of interface prototype object's \"constructor\" property","status":"PASS"},{"name":"ResizeObserverEntry interface: existence and properties of interface prototype object's @@unscopables property","status":"PASS"},{"name":"ResizeObserverEntry interface: attribute target","status":"PASS"},{"name":"ResizeObserverEntry interface: attribute contentRect","status":"PASS"},{"name":"ResizeObserverEntry interface: attribute borderBoxSize","status":"FAIL"},{"name":"ResizeObserverEntry interface: attribute contentBoxSize","status":"FAIL"},{"name":"ResizeObserverEntry interface: attribute devicePixelContentBoxSize","status":"FAIL"},{"name":"ResizeObserverEntry must be primary interface of entry","status":"PASS"},{"name":"Stringification of entry","status":"PASS"},{"name":"ResizeObserverEntry interface: entry must inherit property \"target\" with the proper type","status":"PASS"},{"name":"ResizeObserverEntry interface: entry must inherit property \"contentRect\" with the proper type","status":"PASS"},{"name":"ResizeObserverEntry interface: entry must inherit property \"borderBoxSize\" with the proper type","status":"FAIL"},{"name":"ResizeObserverEntry interface: entry must inherit property \"contentBoxSize\" with the proper type","status":"FAIL"},{"name":"ResizeObserverEntry interface: entry must inherit property \"devicePixelContentBoxSize\" with the proper type","status":"FAIL"},{"name":"ResizeObserverSize interface: existence and properties of interface object","status":"FAIL"},{"name":"ResizeObserverSize interface object length","status":"FAIL"},{"name":"ResizeObserverSize interface object name","status":"FAIL"},{"name":"ResizeObserverSize interface: existence and properties of interface prototype object","status":"FAIL"},{"name":"ResizeObserverSize interface: existence and properties of interface prototype object's \"constructor\" property","status":"FAIL"},{"name":"ResizeObserverSize interface: existence and properties of interface prototype object's @@unscopables property","status":"FAIL"},{"name":"ResizeObserverSize interface: attribute inlineSize","status":"FAIL"},{"name":"ResizeObserverSize interface: attribute blockSize","status":"FAIL"},{"name":"ResizeObservation interface: existence and properties of interface object","status":"FAIL"},{"name":"ResizeObservation interface object length","status":"FAIL"},{"name":"ResizeObservation interface object name","status":"FAIL"},{"name":"ResizeObservation interface: existence and properties of interface prototype object","status":"FAIL"},{"name":"ResizeObservation interface: existence and properties of interface prototype object's \"constructor\" property","status":"FAIL"},{"name":"ResizeObservation interface: existence and properties of interface prototype object's @@unscopables property","status":"FAIL"},{"name":"ResizeObservation interface: attribute target","status":"FAIL"},{"name":"ResizeObservation interface: attribute observedBox","status":"FAIL"},{"name":"ResizeObservation interface: attribute lastReportedSize","status":"FAIL"}]}