{"status":"OK","subtests":[{"name":"number: Infinity","status":"PASS"},{"name":"bigint: -12345678901234567890","status":"PASS"},{"name":"bigint: -1","status":"PASS"},{"name":"bigint: 0","status":"PASS"},{"name":"bigint: 1","status":"PASS"},{"name":"bigint: 12345678901234567890","status":"PASS"},{"name":"string: ","status":"PASS"},{"name":"string: this is a sample string","status":"PASS"},{"name":"string: null(\u0000)","status":"PASS"},{"name":"Boolean: false","status":"PASS"},{"name":"Boolean: true","status":"PASS"},{"name":"Number: NaN","status":"PASS"},{"name":"Number: -Infinity","status":"PASS"},{"name":"Number: -1.7976931348623157e+308","status":"PASS"},{"name":"Number: -4294967295","status":"PASS"},{"name":"Number: -2147483648","status":"PASS"},{"name":"Number: -2147483647","status":"PASS"},{"name":"Number: -1","status":"PASS"},{"name":"Number: -5e-324","status":"PASS"},{"name":"Number: -0","status":"PASS"}]}