{"status":"OK","subtests":[{"name":"Number: 0","status":"FAIL"},{"name":"Number: 1","status":"FAIL"},{"name":"Number: 5e-324","status":"FAIL"},{"name":"Number: 2147483647","status":"FAIL"},{"name":"Number: 2147483648","status":"FAIL"},{"name":"Number: 4294967295","status":"FAIL"},{"name":"Number: 1.7976931348623157e+308","status":"FAIL"},{"name":"Number: Infinity","status":"FAIL"},{"name":"BigInt: -12345678901234567890","status":"FAIL"},{"name":"BigInt: -1","status":"FAIL"},{"name":"BigInt: 0","status":"FAIL"},{"name":"BigInt: 1","status":"FAIL"},{"name":"BigInt: 12345678901234567890","status":"FAIL"},{"name":"String: ","status":"FAIL"},{"name":"String: this is a sample string","status":"FAIL"},{"name":"String: null(\u0000)","status":"FAIL"},{"name":"Date: Mon Feb 10 1653 06:13:20 GMT+0000 (Coordinated Universal Time)","status":"FAIL"},{"name":"Date: Sun Apr 24 1938 22:13:20 GMT+0000 (Coordinated Universal Time)","status":"FAIL"},{"name":"Date: Sat Dec 20 1969 10:13:20 GMT+0000 (Coordinated Universal Time)","status":"FAIL"},{"name":"Date: Wed Dec 31 1969 23:43:20 GMT+0000 (Coordinated Universal Time)","status":"FAIL"}]}