{"status":"OK","subtests":[{"name":"delete at <span style=\"white-space:nowrap\">abc[</span><div style=\"white-space:pre-line\">]def\\nghi</div>","status":"FAIL"},{"name":"delete at <span style=\"white-space:nowrap\">abc[</span><div class=\"preLine\">]def\\nghi</div>","status":"FAIL"},{"name":"delete at <span class=\"nowrap\">abc[</span><div style=\"white-space:pre-line\">]def\\nghi</div>","status":"FAIL"},{"name":"delete at <span style=\"white-space:nowrap\">abc[</span><div style=\"white-space:pre-line\">]def<br>ghi</div>","status":"PASS"},{"name":"delete at <span style=\"white-space:nowrap\">abc[</span><div class=\"preLine\">]def<br>ghi</div>","status":"PASS"},{"name":"delete at <span class=\"nowrap\">abc[</span><div style=\"white-space:pre-line\">]def<br>ghi</div>","status":"PASS"},{"name":"delete at <span style=\"white-space:nowrap\">abc[</span><div style=\"white-space:pre-line\"><b>]def\\nghi</b></div>","status":"FAIL"},{"name":"delete at <span style=\"white-space:nowrap\">abc[</span><div class=\"preLine\"><b>]def\\nghi</b></div>","status":"FAIL"},{"name":"delete at <span class=\"nowrap\">abc[</span><div style=\"white-space:pre-line\"><b>]def\\nghi</b></div>","status":"FAIL"},{"name":"delete at <span style=\"white-space:nowrap\">abc[</span><div style=\"white-space:pre-line\"><b>]def<br>ghi</b></div>","status":"PASS"},{"name":"delete at <span style=\"white-space:nowrap\">abc[</span><div class=\"preLine\"><b>]def<br>ghi</b></div>","status":"PASS"},{"name":"delete at <span class=\"nowrap\">abc[</span><div style=\"white-space:pre-line\"><b>]def<br>ghi</b></div>","status":"PASS"},{"name":"delete at <span style=\"white-space:nowrap\">abc[</span><div style=\"white-space:pre-line\"><b>]def</b>ghi\\njkl</div>","status":"PASS"},{"name":"delete at <span style=\"white-space:nowrap\">abc[</span><div class=\"preLine\"><b>]def</b>ghi\\njkl</div>","status":"PASS"},{"name":"delete at <span class=\"nowrap\">abc[</span><div style=\"white-space:pre-line\"><b>]def</b>ghi\\njkl</div>","status":"PASS"},{"name":"delete at <span style=\"white-space:nowrap\">abc[</span><div style=\"white-space:pre-line\"><b>]def</b>ghi<br>jkl</div>","status":"PASS"},{"name":"delete at <span style=\"white-space:nowrap\">abc[</span><div class=\"preLine\"><b>]def</b>ghi<br>jkl</div>","status":"PASS"},{"name":"delete at <span class=\"nowrap\">abc[</span><div style=\"white-space:pre-line\"><b>]def</b>ghi<br>jkl</div>","status":"PASS"},{"name":"delete at <span style=\"white-space:nowrap\">abc[</span><div style=\"white-space:pre-line\"><b>]def</b>\\nghi</div>","status":"PASS"},{"name":"delete at <span style=\"white-space:nowrap\">abc[</span><div class=\"preLine\"><b>]def</b>\\nghi</div>","status":"PASS"},{"name":"delete at <span class=\"nowrap\">abc[</span><div style=\"white-space:pre-line\"><b>]def</b>\\nghi</div>","status":"PASS"},{"name":"delete at <span style=\"white-space:nowrap\">abc[</span><div style=\"white-space:pre-line\"><b>]def</b><br>ghi</div>","status":"PASS"},{"name":"delete at <span style=\"white-space:nowrap\">abc[</span><div class=\"preLine\"><b>]def</b><br>ghi</div>","status":"PASS"},{"name":"delete at <span class=\"nowrap\">abc[</span><div style=\"white-space:pre-line\"><b>]def</b><br>ghi</div>","status":"PASS"},{"name":"delete at <span style=\"white-space:nowrap\">abc[</span><div style=\"white-space:pre-line\"><b>]def\\n</b>ghi</div>","status":"FAIL"},{"name":"delete at <span style=\"white-space:nowrap\">abc[</span><div class=\"preLine\"><b>]def\\n</b>ghi</div>","status":"FAIL"},{"name":"delete at <span class=\"nowrap\">abc[</span><div style=\"white-space:pre-line\"><b>]def\\n</b>ghi</div>","status":"FAIL"},{"name":"delete at <span style=\"white-space:nowrap\">abc[</span><div style=\"white-space:pre-line\"><b>]def<br></b>ghi</div>","status":"PASS"},{"name":"delete at <span style=\"white-space:nowrap\">abc[</span><div class=\"preLine\"><b>]def<br></b>ghi</div>","status":"PASS"},{"name":"delete at <span class=\"nowrap\">abc[</span><div style=\"white-space:pre-line\"><b>]def<br></b>ghi</div>","status":"PASS"},{"name":"delete at <span style=\"white-space:nowrap\">abc[</span><div style=\"white-space:pre-line\"><div>]def</div>ghi</div>","status":"PASS"},{"name":"delete at <span style=\"white-space:nowrap\">abc[</span><div class=\"preLine\"><div>]def</div>ghi</div>","status":"PASS"},{"name":"delete at <span class=\"nowrap\">abc[</span><div style=\"white-space:pre-line\"><div>]def</div>ghi</div>","status":"PASS"},{"name":"delete at <span style=\"white-space:nowrap\">abc[</span><div style=\"white-space:pre-line\">]def<div>ghi</div></div>","status":"PASS"},{"name":"delete at <span style=\"white-space:nowrap\">abc[</span><div class=\"preLine\">]def<div>ghi</div></div>","status":"PASS"},{"name":"delete at <span class=\"nowrap\">abc[</span><div style=\"white-space:pre-line\">]def<div>ghi</div></div>","status":"PASS"},{"name":"delete at <span style=\"white-space:nowrap\">abc[</span><div style=\"white-space:pre-line\"><div>]def</div>ghi\\njkl</div>","status":"PASS"},{"name":"delete at <span style=\"white-space:nowrap\">abc[</span><div class=\"preLine\"><div>]def</div>ghi\\njkl</div>","status":"PASS"},{"name":"delete at <span class=\"nowrap\">abc[</span><div style=\"white-space:pre-line\"><div>]def</div>ghi\\njkl</div>","status":"PASS"},{"name":"delete at <span style=\"white-space:nowrap\">abc[</span><div style=\"white-space:pre-line\"><div>]def</div>ghi<br>jkl</div>","status":"PASS"},{"name":"delete at <span style=\"white-space:nowrap\">abc[</span><div class=\"preLine\"><div>]def</div>ghi<br>jkl</div>","status":"PASS"},{"name":"delete at <span class=\"nowrap\">abc[</span><div style=\"white-space:pre-line\"><div>]def</div>ghi<br>jkl</div>","status":"PASS"},{"name":"delete at <span style=\"white-space:nowrap\">abc[</span><div style=\"white-space:pre-line\">]def<div>ghi</div>\\njkl</div>","status":"PASS"},{"name":"delete at <span style=\"white-space:nowrap\">abc[</span><div class=\"preLine\">]def<div>ghi</div>\\njkl</div>","status":"PASS"},{"name":"delete at <span class=\"nowrap\">abc[</span><div style=\"white-space:pre-line\">]def<div>ghi</div>\\njkl</div>","status":"PASS"},{"name":"delete at <span style=\"white-space:nowrap\">abc[</span><div style=\"white-space:pre-line\">]def<div>ghi</div><br>jkl</div>","status":"PASS"},{"name":"delete at <span style=\"white-space:nowrap\">abc[</span><div class=\"preLine\">]def<div>ghi</div><br>jkl</div>","status":"PASS"},{"name":"delete at <span class=\"nowrap\">abc[</span><div style=\"white-space:pre-line\">]def<div>ghi</div><br>jkl</div>","status":"PASS"},{"name":"delete at <span style=\"white-space:nowrap\">abc[</span><div style=\"white-space:pre-line\"><div>]def\\nghi</div>jkl\\nmno</div>","status":"FAIL"},{"name":"delete at <span style=\"white-space:nowrap\">abc[</span><div class=\"preLine\"><div>]def\\nghi</div>jkl\\nmno</div>","status":"FAIL"},{"name":"delete at <span class=\"nowrap\">abc[</span><div style=\"white-space:pre-line\"><div>]def\\nghi</div>jkl\\nmno</div>","status":"FAIL"},{"name":"delete at <span style=\"white-space:nowrap\">abc[</span><div style=\"white-space:pre-line\"><div>]def<br>ghi</div>jkl<br>mno</div>","status":"PASS"},{"name":"delete at <span style=\"white-space:nowrap\">abc[</span><div class=\"preLine\"><div>]def<br>ghi</div>jkl<br>mno</div>","status":"PASS"},{"name":"delete at <span class=\"nowrap\">abc[</span><div style=\"white-space:pre-line\"><div>]def<br>ghi</div>jkl<br>mno</div>","status":"PASS"},{"name":"delete at <span style=\"white-space:nowrap\">abc[</span><div style=\"white-space:pre-line\">]def<div>ghi</div>jkl\\nmno</div>","status":"PASS"},{"name":"delete at <span style=\"white-space:nowrap\">abc[</span><div class=\"preLine\">]def<div>ghi</div>jkl\\nmno</div>","status":"PASS"},{"name":"delete at <span class=\"nowrap\">abc[</span><div style=\"white-space:pre-line\">]def<div>ghi</div>jkl\\nmno</div>","status":"PASS"},{"name":"delete at <span style=\"white-space:nowrap\">abc[</span><div style=\"white-space:pre-line\">]def<div>ghi</div>jkl<br>mno</div>","status":"PASS"},{"name":"delete at <span style=\"white-space:nowrap\">abc[</span><div class=\"preLine\">]def<div>ghi</div>jkl<br>mno</div>","status":"PASS"},{"name":"delete at <span class=\"nowrap\">abc[</span><div style=\"white-space:pre-line\">]def<div>ghi</div>jkl<br>mno</div>","status":"PASS"}]}