{"status":"OK","subtests":[{"name":"webgpu:api/validation/createBindGroup:binding_count_mismatch=","status":"FAIL"},{"name":"webgpu:api/validation/createBindGroup:binding_must_be_present_in_layout=","status":"FAIL"},{"name":"webgpu:api/validation/createBindGroup:buffer_binding_must_contain_exactly_one_buffer_of_its_type={\"bindingType\":\"uniform-buffer\",\"resourceType\":\"error-buffer\"}","status":"FAIL"},{"name":"webgpu:api/validation/createBindGroup:buffer_binding_must_contain_exactly_one_buffer_of_its_type={\"bindingType\":\"uniform-buffer\",\"resourceType\":\"error-sampler\"}","status":"FAIL"},{"name":"webgpu:api/validation/createBindGroup:buffer_binding_must_contain_exactly_one_buffer_of_its_type={\"bindingType\":\"uniform-buffer\",\"resourceType\":\"error-textureview\"}","status":"FAIL"},{"name":"webgpu:api/validation/createBindGroup:buffer_binding_must_contain_exactly_one_buffer_of_its_type={\"bindingType\":\"uniform-buffer\",\"resourceType\":\"uniform-buffer\"}","status":"FAIL"},{"name":"webgpu:api/validation/createBindGroup:buffer_binding_must_contain_exactly_one_buffer_of_its_type={\"bindingType\":\"uniform-buffer\",\"resourceType\":\"storage-buffer\"}","status":"FAIL"},{"name":"webgpu:api/validation/createBindGroup:buffer_binding_must_contain_exactly_one_buffer_of_its_type={\"bindingType\":\"uniform-buffer\",\"resourceType\":\"sampler\"}","status":"FAIL"},{"name":"webgpu:api/validation/createBindGroup:buffer_binding_must_contain_exactly_one_buffer_of_its_type={\"bindingType\":\"uniform-buffer\",\"resourceType\":\"sampled-textureview\"}","status":"FAIL"},{"name":"webgpu:api/validation/createBindGroup:buffer_binding_must_contain_exactly_one_buffer_of_its_type={\"bindingType\":\"uniform-buffer\",\"resourceType\":\"storage-textureview\"}","status":"FAIL"},{"name":"webgpu:api/validation/createBindGroup:buffer_binding_must_contain_exactly_one_buffer_of_its_type={\"bindingType\":\"storage-buffer\",\"resourceType\":\"error-buffer\"}","status":"FAIL"},{"name":"webgpu:api/validation/createBindGroup:buffer_binding_must_contain_exactly_one_buffer_of_its_type={\"bindingType\":\"storage-buffer\",\"resourceType\":\"error-sampler\"}","status":"FAIL"},{"name":"webgpu:api/validation/createBindGroup:buffer_binding_must_contain_exactly_one_buffer_of_its_type={\"bindingType\":\"storage-buffer\",\"resourceType\":\"error-textureview\"}","status":"FAIL"},{"name":"webgpu:api/validation/createBindGroup:buffer_binding_must_contain_exactly_one_buffer_of_its_type={\"bindingType\":\"storage-buffer\",\"resourceType\":\"uniform-buffer\"}","status":"FAIL"},{"name":"webgpu:api/validation/createBindGroup:buffer_binding_must_contain_exactly_one_buffer_of_its_type={\"bindingType\":\"storage-buffer\",\"resourceType\":\"storage-buffer\"}","status":"FAIL"},{"name":"webgpu:api/validation/createBindGroup:buffer_binding_must_contain_exactly_one_buffer_of_its_type={\"bindingType\":\"storage-buffer\",\"resourceType\":\"sampler\"}","status":"FAIL"},{"name":"webgpu:api/validation/createBindGroup:buffer_binding_must_contain_exactly_one_buffer_of_its_type={\"bindingType\":\"storage-buffer\",\"resourceType\":\"sampled-textureview\"}","status":"FAIL"},{"name":"webgpu:api/validation/createBindGroup:buffer_binding_must_contain_exactly_one_buffer_of_its_type={\"bindingType\":\"storage-buffer\",\"resourceType\":\"storage-textureview\"}","status":"FAIL"},{"name":"webgpu:api/validation/createBindGroup:buffer_binding_must_contain_exactly_one_buffer_of_its_type={\"bindingType\":\"readonly-storage-buffer\",\"resourceType\":\"error-buffer\"}","status":"FAIL"},{"name":"webgpu:api/validation/createBindGroup:buffer_binding_must_contain_exactly_one_buffer_of_its_type={\"bindingType\":\"readonly-storage-buffer\",\"resourceType\":\"error-sampler\"}","status":"FAIL"},{"name":"webgpu:api/validation/createBindGroup:buffer_binding_must_contain_exactly_one_buffer_of_its_type={\"bindingType\":\"readonly-storage-buffer\",\"resourceType\":\"error-textureview\"}","status":"FAIL"},{"name":"webgpu:api/validation/createBindGroup:buffer_binding_must_contain_exactly_one_buffer_of_its_type={\"bindingType\":\"readonly-storage-buffer\",\"resourceType\":\"uniform-buffer\"}","status":"FAIL"},{"name":"webgpu:api/validation/createBindGroup:buffer_binding_must_contain_exactly_one_buffer_of_its_type={\"bindingType\":\"readonly-storage-buffer\",\"resourceType\":\"storage-buffer\"}","status":"FAIL"},{"name":"webgpu:api/validation/createBindGroup:buffer_binding_must_contain_exactly_one_buffer_of_its_type={\"bindingType\":\"readonly-storage-buffer\",\"resourceType\":\"sampler\"}","status":"FAIL"},{"name":"webgpu:api/validation/createBindGroup:buffer_binding_must_contain_exactly_one_buffer_of_its_type={\"bindingType\":\"readonly-storage-buffer\",\"resourceType\":\"sampled-textureview\"}","status":"FAIL"},{"name":"webgpu:api/validation/createBindGroup:buffer_binding_must_contain_exactly_one_buffer_of_its_type={\"bindingType\":\"readonly-storage-buffer\",\"resourceType\":\"storage-textureview\"}","status":"FAIL"},{"name":"webgpu:api/validation/createBindGroup:buffer_binding_must_contain_exactly_one_buffer_of_its_type={\"bindingType\":\"sampler\",\"resourceType\":\"error-buffer\"}","status":"FAIL"},{"name":"webgpu:api/validation/createBindGroup:buffer_binding_must_contain_exactly_one_buffer_of_its_type={\"bindingType\":\"sampler\",\"resourceType\":\"error-sampler\"}","status":"FAIL"},{"name":"webgpu:api/validation/createBindGroup:buffer_binding_must_contain_exactly_one_buffer_of_its_type={\"bindingType\":\"sampler\",\"resourceType\":\"error-textureview\"}","status":"FAIL"},{"name":"webgpu:api/validation/createBindGroup:buffer_binding_must_contain_exactly_one_buffer_of_its_type={\"bindingType\":\"sampler\",\"resourceType\":\"uniform-buffer\"}","status":"FAIL"},{"name":"webgpu:api/validation/createBindGroup:buffer_binding_must_contain_exactly_one_buffer_of_its_type={\"bindingType\":\"sampler\",\"resourceType\":\"storage-buffer\"}","status":"FAIL"},{"name":"webgpu:api/validation/createBindGroup:buffer_binding_must_contain_exactly_one_buffer_of_its_type={\"bindingType\":\"sampler\",\"resourceType\":\"sampler\"}","status":"FAIL"},{"name":"webgpu:api/validation/createBindGroup:buffer_binding_must_contain_exactly_one_buffer_of_its_type={\"bindingType\":\"sampler\",\"resourceType\":\"sampled-textureview\"}","status":"FAIL"},{"name":"webgpu:api/validation/createBindGroup:buffer_binding_must_contain_exactly_one_buffer_of_its_type={\"bindingType\":\"sampler\",\"resourceType\":\"storage-textureview\"}","status":"FAIL"},{"name":"webgpu:api/validation/createBindGroup:buffer_binding_must_contain_exactly_one_buffer_of_its_type={\"bindingType\":\"comparison-sampler\",\"resourceType\":\"error-buffer\"}","status":"FAIL"},{"name":"webgpu:api/validation/createBindGroup:buffer_binding_must_contain_exactly_one_buffer_of_its_type={\"bindingType\":\"comparison-sampler\",\"resourceType\":\"error-sampler\"}","status":"FAIL"},{"name":"webgpu:api/validation/createBindGroup:buffer_binding_must_contain_exactly_one_buffer_of_its_type={\"bindingType\":\"comparison-sampler\",\"resourceType\":\"error-textureview\"}","status":"FAIL"},{"name":"webgpu:api/validation/createBindGroup:buffer_binding_must_contain_exactly_one_buffer_of_its_type={\"bindingType\":\"comparison-sampler\",\"resourceType\":\"uniform-buffer\"}","status":"FAIL"},{"name":"webgpu:api/validation/createBindGroup:buffer_binding_must_contain_exactly_one_buffer_of_its_type={\"bindingType\":\"comparison-sampler\",\"resourceType\":\"storage-buffer\"}","status":"FAIL"},{"name":"webgpu:api/validation/createBindGroup:buffer_binding_must_contain_exactly_one_buffer_of_its_type={\"bindingType\":\"comparison-sampler\",\"resourceType\":\"sampler\"}","status":"FAIL"},{"name":"webgpu:api/validation/createBindGroup:buffer_binding_must_contain_exactly_one_buffer_of_its_type={\"bindingType\":\"comparison-sampler\",\"resourceType\":\"sampled-textureview\"}","status":"FAIL"},{"name":"webgpu:api/validation/createBindGroup:buffer_binding_must_contain_exactly_one_buffer_of_its_type={\"bindingType\":\"comparison-sampler\",\"resourceType\":\"storage-textureview\"}","status":"FAIL"},{"name":"webgpu:api/validation/createBindGroup:buffer_binding_must_contain_exactly_one_buffer_of_its_type={\"bindingType\":\"sampled-texture\",\"resourceType\":\"error-buffer\"}","status":"FAIL"},{"name":"webgpu:api/validation/createBindGroup:buffer_binding_must_contain_exactly_one_buffer_of_its_type={\"bindingType\":\"sampled-texture\",\"resourceType\":\"error-sampler\"}","status":"FAIL"},{"name":"webgpu:api/validation/createBindGroup:buffer_binding_must_contain_exactly_one_buffer_of_its_type={\"bindingType\":\"sampled-texture\",\"resourceType\":\"error-textureview\"}","status":"FAIL"},{"name":"webgpu:api/validation/createBindGroup:buffer_binding_must_contain_exactly_one_buffer_of_its_type={\"bindingType\":\"sampled-texture\",\"resourceType\":\"uniform-buffer\"}","status":"FAIL"},{"name":"webgpu:api/validation/createBindGroup:buffer_binding_must_contain_exactly_one_buffer_of_its_type={\"bindingType\":\"sampled-texture\",\"resourceType\":\"storage-buffer\"}","status":"FAIL"},{"name":"webgpu:api/validation/createBindGroup:buffer_binding_must_contain_exactly_one_buffer_of_its_type={\"bindingType\":\"sampled-texture\",\"resourceType\":\"sampler\"}","status":"FAIL"},{"name":"webgpu:api/validation/createBindGroup:buffer_binding_must_contain_exactly_one_buffer_of_its_type={\"bindingType\":\"sampled-texture\",\"resourceType\":\"sampled-textureview\"}","status":"FAIL"},{"name":"webgpu:api/validation/createBindGroup:buffer_binding_must_contain_exactly_one_buffer_of_its_type={\"bindingType\":\"sampled-texture\",\"resourceType\":\"storage-textureview\"}","status":"FAIL"},{"name":"webgpu:api/validation/createBindGroup:buffer_binding_must_contain_exactly_one_buffer_of_its_type={\"bindingType\":\"writeonly-storage-texture\",\"resourceType\":\"error-buffer\"}","status":"FAIL"},{"name":"webgpu:api/validation/createBindGroup:buffer_binding_must_contain_exactly_one_buffer_of_its_type={\"bindingType\":\"writeonly-storage-texture\",\"resourceType\":\"error-sampler\"}","status":"FAIL"},{"name":"webgpu:api/validation/createBindGroup:buffer_binding_must_contain_exactly_one_buffer_of_its_type={\"bindingType\":\"writeonly-storage-texture\",\"resourceType\":\"error-textureview\"}","status":"FAIL"},{"name":"webgpu:api/validation/createBindGroup:buffer_binding_must_contain_exactly_one_buffer_of_its_type={\"bindingType\":\"writeonly-storage-texture\",\"resourceType\":\"uniform-buffer\"}","status":"FAIL"},{"name":"webgpu:api/validation/createBindGroup:buffer_binding_must_contain_exactly_one_buffer_of_its_type={\"bindingType\":\"writeonly-storage-texture\",\"resourceType\":\"storage-buffer\"}","status":"FAIL"},{"name":"webgpu:api/validation/createBindGroup:buffer_binding_must_contain_exactly_one_buffer_of_its_type={\"bindingType\":\"writeonly-storage-texture\",\"resourceType\":\"sampler\"}","status":"FAIL"},{"name":"webgpu:api/validation/createBindGroup:buffer_binding_must_contain_exactly_one_buffer_of_its_type={\"bindingType\":\"writeonly-storage-texture\",\"resourceType\":\"sampled-textureview\"}","status":"FAIL"},{"name":"webgpu:api/validation/createBindGroup:buffer_binding_must_contain_exactly_one_buffer_of_its_type={\"bindingType\":\"writeonly-storage-texture\",\"resourceType\":\"storage-textureview\"}","status":"FAIL"},{"name":"webgpu:api/validation/createBindGroup:buffer_binding_must_contain_exactly_one_buffer_of_its_type={\"bindingType\":\"readonly-storage-texture\",\"resourceType\":\"error-buffer\"}","status":"FAIL"},{"name":"webgpu:api/validation/createBindGroup:buffer_binding_must_contain_exactly_one_buffer_of_its_type={\"bindingType\":\"readonly-storage-texture\",\"resourceType\":\"error-sampler\"}","status":"FAIL"},{"name":"webgpu:api/validation/createBindGroup:buffer_binding_must_contain_exactly_one_buffer_of_its_type={\"bindingType\":\"readonly-storage-texture\",\"resourceType\":\"error-textureview\"}","status":"FAIL"},{"name":"webgpu:api/validation/createBindGroup:buffer_binding_must_contain_exactly_one_buffer_of_its_type={\"bindingType\":\"readonly-storage-texture\",\"resourceType\":\"uniform-buffer\"}","status":"FAIL"},{"name":"webgpu:api/validation/createBindGroup:buffer_binding_must_contain_exactly_one_buffer_of_its_type={\"bindingType\":\"readonly-storage-texture\",\"resourceType\":\"storage-buffer\"}","status":"FAIL"},{"name":"webgpu:api/validation/createBindGroup:buffer_binding_must_contain_exactly_one_buffer_of_its_type={\"bindingType\":\"readonly-storage-texture\",\"resourceType\":\"sampler\"}","status":"FAIL"},{"name":"webgpu:api/validation/createBindGroup:buffer_binding_must_contain_exactly_one_buffer_of_its_type={\"bindingType\":\"readonly-storage-texture\",\"resourceType\":\"sampled-textureview\"}","status":"FAIL"},{"name":"webgpu:api/validation/createBindGroup:buffer_binding_must_contain_exactly_one_buffer_of_its_type={\"bindingType\":\"readonly-storage-texture\",\"resourceType\":\"storage-textureview\"}","status":"FAIL"},{"name":"webgpu:api/validation/createBindGroup:texture_binding_must_have_correct_usage={\"type\":\"sampled-texture\"}","status":"FAIL"},{"name":"webgpu:api/validation/createBindGroup:texture_binding_must_have_correct_usage={\"type\":\"storage-texture\"}","status":"FAIL"},{"name":"webgpu:api/validation/createBindGroup:texture_must_have_correct_component_type={\"textureComponentType\":\"float\"}","status":"FAIL"},{"name":"webgpu:api/validation/createBindGroup:texture_must_have_correct_component_type={\"textureComponentType\":\"sint\"}","status":"FAIL"},{"name":"webgpu:api/validation/createBindGroup:texture_must_have_correct_component_type={\"textureComponentType\":\"uint\"}","status":"FAIL"},{"name":"webgpu:api/validation/createBindGroup:texture_must_have_correct_dimension=","status":"FAIL"},{"name":"webgpu:api/validation/createBindGroup:buffer_offset_and_size_for_bind_groups_match={\"offset\":0,\"size\":512}","status":"FAIL"},{"name":"webgpu:api/validation/createBindGroup:buffer_offset_and_size_for_bind_groups_match={\"offset\":256,\"size\":256}","status":"FAIL"},{"name":"webgpu:api/validation/createBindGroup:buffer_offset_and_size_for_bind_groups_match={\"offset\":0,\"size\":1024}","status":"FAIL"},{"name":"webgpu:api/validation/createBindGroup:buffer_offset_and_size_for_bind_groups_match={\"offset\":0}","status":"FAIL"},{"name":"webgpu:api/validation/createBindGroup:buffer_offset_and_size_for_bind_groups_match={\"offset\":768,\"size\":256}","status":"FAIL"},{"name":"webgpu:api/validation/createBindGroup:buffer_offset_and_size_for_bind_groups_match={\"offset\":768}","status":"FAIL"},{"name":"webgpu:api/validation/createBindGroup:buffer_offset_and_size_for_bind_groups_match={\"offset\":0,\"size\":0}","status":"FAIL"},{"name":"webgpu:api/validation/createBindGroup:buffer_offset_and_size_for_bind_groups_match={\"offset\":256,\"size\":0}","status":"FAIL"},{"name":"webgpu:api/validation/createBindGroup:buffer_offset_and_size_for_bind_groups_match={\"offset\":1024,\"size\":0}","status":"FAIL"},{"name":"webgpu:api/validation/createBindGroup:buffer_offset_and_size_for_bind_groups_match={\"offset\":1024}","status":"FAIL"},{"name":"webgpu:api/validation/createBindGroup:buffer_offset_and_size_for_bind_groups_match={\"offset\":1,\"size\":256}","status":"FAIL"},{"name":"webgpu:api/validation/createBindGroup:buffer_offset_and_size_for_bind_groups_match={\"offset\":1}","status":"FAIL"},{"name":"webgpu:api/validation/createBindGroup:buffer_offset_and_size_for_bind_groups_match={\"offset\":128,\"size\":256}","status":"FAIL"},{"name":"webgpu:api/validation/createBindGroup:buffer_offset_and_size_for_bind_groups_match={\"offset\":255,\"size\":256}","status":"FAIL"},{"name":"webgpu:api/validation/createBindGroup:buffer_offset_and_size_for_bind_groups_match={\"offset\":1280,\"size\":0}","status":"FAIL"},{"name":"webgpu:api/validation/createBindGroup:buffer_offset_and_size_for_bind_groups_match={\"offset\":0,\"size\":1280}","status":"FAIL"},{"name":"webgpu:api/validation/createBindGroup:buffer_offset_and_size_for_bind_groups_match={\"offset\":1024,\"size\":1}","status":"FAIL"},{"name":"webgpu:api/validation/createBindGroupLayout:some_binding_index_was_specified_more_than_once=","status":"FAIL"},{"name":"webgpu:api/validation/createBindGroupLayout:Visibility_of_bindings_can_be_0=","status":"FAIL"},{"name":"webgpu:api/validation/createBindGroupLayout:number_of_dynamic_buffers_exceeds_the_maximum_value={\"type\":\"storage-buffer\",\"maxDynamicBufferCount\":4}","status":"FAIL"},{"name":"webgpu:api/validation/createBindGroupLayout:number_of_dynamic_buffers_exceeds_the_maximum_value={\"type\":\"uniform-buffer\",\"maxDynamicBufferCount\":8}","status":"FAIL"},{"name":"webgpu:api/validation/createBindGroupLayout:dynamic_set_to_true_is_allowed_only_for_buffers={\"type\":\"uniform-buffer\"}","status":"FAIL"},{"name":"webgpu:api/validation/createBindGroupLayout:dynamic_set_to_true_is_allowed_only_for_buffers={\"type\":\"storage-buffer\"}","status":"FAIL"},{"name":"webgpu:api/validation/createBindGroupLayout:dynamic_set_to_true_is_allowed_only_for_buffers={\"type\":\"readonly-storage-buffer\"}","status":"FAIL"},{"name":"webgpu:api/validation/createBindGroupLayout:dynamic_set_to_true_is_allowed_only_for_buffers={\"type\":\"sampler\"}","status":"FAIL"},{"name":"webgpu:api/validation/createBindGroupLayout:dynamic_set_to_true_is_allowed_only_for_buffers={\"type\":\"comparison-sampler\"}","status":"FAIL"},{"name":"webgpu:api/validation/createBindGroupLayout:dynamic_set_to_true_is_allowed_only_for_buffers={\"type\":\"sampled-texture\"}","status":"FAIL"},{"name":"webgpu:api/validation/createBindGroupLayout:dynamic_set_to_true_is_allowed_only_for_buffers={\"type\":\"writeonly-storage-texture\"}","status":"FAIL"},{"name":"webgpu:api/validation/createBindGroupLayout:dynamic_set_to_true_is_allowed_only_for_buffers={\"type\":\"readonly-storage-texture\"}","status":"FAIL"},{"name":"webgpu:api/validation/createBindGroupLayout:max_resources_per_stage/in_bind_group_layout={\"maxedType\":\"uniform-buffer\",\"maxedVisibility\":1,\"extraType\":\"uniform-buffer\",\"extraVisibility\":1}","status":"FAIL"},{"name":"webgpu:api/validation/createBindGroupLayout:max_resources_per_stage/in_bind_group_layout={\"maxedType\":\"uniform-buffer\",\"maxedVisibility\":1,\"extraType\":\"uniform-buffer\",\"extraVisibility\":2}","status":"FAIL"},{"name":"webgpu:api/validation/createBindGroupLayout:max_resources_per_stage/in_bind_group_layout={\"maxedType\":\"uniform-buffer\",\"maxedVisibility\":1,\"extraType\":\"uniform-buffer\",\"extraVisibility\":4}","status":"FAIL"},{"name":"webgpu:api/validation/createBindGroupLayout:max_resources_per_stage/in_bind_group_layout={\"maxedType\":\"uniform-buffer\",\"maxedVisibility\":1,\"extraType\":\"sampler\",\"extraVisibility\":1}","status":"FAIL"},{"name":"webgpu:api/validation/createBindGroupLayout:max_resources_per_stage/in_bind_group_layout={\"maxedType\":\"uniform-buffer\",\"maxedVisibility\":1,\"extraType\":\"sampler\",\"extraVisibility\":2}","status":"FAIL"},{"name":"webgpu:api/validation/createBindGroupLayout:max_resources_per_stage/in_bind_group_layout={\"maxedType\":\"uniform-buffer\",\"maxedVisibility\":1,\"extraType\":\"sampler\",\"extraVisibility\":4}","status":"FAIL"},{"name":"webgpu:api/validation/createBindGroupLayout:max_resources_per_stage/in_bind_group_layout={\"maxedType\":\"uniform-buffer\",\"maxedVisibility\":2,\"extraType\":\"uniform-buffer\",\"extraVisibility\":1}","status":"FAIL"},{"name":"webgpu:api/validation/createBindGroupLayout:max_resources_per_stage/in_bind_group_layout={\"maxedType\":\"uniform-buffer\",\"maxedVisibility\":2,\"extraType\":\"uniform-buffer\",\"extraVisibility\":2}","status":"FAIL"},{"name":"webgpu:api/validation/createBindGroupLayout:max_resources_per_stage/in_bind_group_layout={\"maxedType\":\"uniform-buffer\",\"maxedVisibility\":2,\"extraType\":\"uniform-buffer\",\"extraVisibility\":4}","status":"FAIL"},{"name":"webgpu:api/validation/createBindGroupLayout:max_resources_per_stage/in_bind_group_layout={\"maxedType\":\"uniform-buffer\",\"maxedVisibility\":2,\"extraType\":\"sampler\",\"extraVisibility\":1}","status":"FAIL"},{"name":"webgpu:api/validation/createBindGroupLayout:max_resources_per_stage/in_bind_group_layout={\"maxedType\":\"uniform-buffer\",\"maxedVisibility\":2,\"extraType\":\"sampler\",\"extraVisibility\":2}","status":"FAIL"},{"name":"webgpu:api/validation/createBindGroupLayout:max_resources_per_stage/in_bind_group_layout={\"maxedType\":\"uniform-buffer\",\"maxedVisibility\":2,\"extraType\":\"sampler\",\"extraVisibility\":4}","status":"FAIL"},{"name":"webgpu:api/validation/createBindGroupLayout:max_resources_per_stage/in_bind_group_layout={\"maxedType\":\"uniform-buffer\",\"maxedVisibility\":4,\"extraType\":\"uniform-buffer\",\"extraVisibility\":1}","status":"FAIL"},{"name":"webgpu:api/validation/createBindGroupLayout:max_resources_per_stage/in_bind_group_layout={\"maxedType\":\"uniform-buffer\",\"maxedVisibility\":4,\"extraType\":\"uniform-buffer\",\"extraVisibility\":2}","status":"FAIL"},{"name":"webgpu:api/validation/createBindGroupLayout:max_resources_per_stage/in_bind_group_layout={\"maxedType\":\"uniform-buffer\",\"maxedVisibility\":4,\"extraType\":\"uniform-buffer\",\"extraVisibility\":4}","status":"FAIL"},{"name":"webgpu:api/validation/createBindGroupLayout:max_resources_per_stage/in_bind_group_layout={\"maxedType\":\"uniform-buffer\",\"maxedVisibility\":4,\"extraType\":\"sampler\",\"extraVisibility\":1}","status":"FAIL"},{"name":"webgpu:api/validation/createBindGroupLayout:max_resources_per_stage/in_bind_group_layout={\"maxedType\":\"uniform-buffer\",\"maxedVisibility\":4,\"extraType\":\"sampler\",\"extraVisibility\":2}","status":"FAIL"},{"name":"webgpu:api/validation/createBindGroupLayout:max_resources_per_stage/in_bind_group_layout={\"maxedType\":\"uniform-buffer\",\"maxedVisibility\":4,\"extraType\":\"sampler\",\"extraVisibility\":4}","status":"FAIL"},{"name":"webgpu:api/validation/createBindGroupLayout:max_resources_per_stage/in_bind_group_layout={\"maxedType\":\"storage-buffer\",\"maxedVisibility\":4,\"extraType\":\"storage-buffer\",\"extraVisibility\":4}","status":"FAIL"},{"name":"webgpu:api/validation/createBindGroupLayout:max_resources_per_stage/in_bind_group_layout={\"maxedType\":\"storage-buffer\",\"maxedVisibility\":4,\"extraType\":\"readonly-storage-buffer\",\"extraVisibility\":1}","status":"FAIL"},{"name":"webgpu:api/validation/createBindGroupLayout:max_resources_per_stage/in_bind_group_layout={\"maxedType\":\"storage-buffer\",\"maxedVisibility\":4,\"extraType\":\"readonly-storage-buffer\",\"extraVisibility\":2}","status":"FAIL"},{"name":"webgpu:api/validation/createBindGroupLayout:max_resources_per_stage/in_bind_group_layout={\"maxedType\":\"storage-buffer\",\"maxedVisibility\":4,\"extraType\":\"readonly-storage-buffer\",\"extraVisibility\":4}","status":"FAIL"},{"name":"webgpu:api/validation/createBindGroupLayout:max_resources_per_stage/in_bind_group_layout={\"maxedType\":\"storage-buffer\",\"maxedVisibility\":4,\"extraType\":\"sampler\",\"extraVisibility\":1}","status":"FAIL"},{"name":"webgpu:api/validation/createBindGroupLayout:max_resources_per_stage/in_bind_group_layout={\"maxedType\":\"storage-buffer\",\"maxedVisibility\":4,\"extraType\":\"sampler\",\"extraVisibility\":2}","status":"FAIL"},{"name":"webgpu:api/validation/createBindGroupLayout:max_resources_per_stage/in_bind_group_layout={\"maxedType\":\"storage-buffer\",\"maxedVisibility\":4,\"extraType\":\"sampler\",\"extraVisibility\":4}","status":"FAIL"},{"name":"webgpu:api/validation/createBindGroupLayout:max_resources_per_stage/in_bind_group_layout={\"maxedType\":\"readonly-storage-buffer\",\"maxedVisibility\":1,\"extraType\":\"storage-buffer\",\"extraVisibility\":4}","status":"FAIL"},{"name":"webgpu:api/validation/createBindGroupLayout:max_resources_per_stage/in_bind_group_layout={\"maxedType\":\"readonly-storage-buffer\",\"maxedVisibility\":1,\"extraType\":\"readonly-storage-buffer\",\"extraVisibility\":1}","status":"FAIL"},{"name":"webgpu:api/validation/createBindGroupLayout:max_resources_per_stage/in_bind_group_layout={\"maxedType\":\"readonly-storage-buffer\",\"maxedVisibility\":1,\"extraType\":\"readonly-storage-buffer\",\"extraVisibility\":2}","status":"FAIL"},{"name":"webgpu:api/validation/createBindGroupLayout:max_resources_per_stage/in_bind_group_layout={\"maxedType\":\"readonly-storage-buffer\",\"maxedVisibility\":1,\"extraType\":\"readonly-storage-buffer\",\"extraVisibility\":4}","status":"FAIL"},{"name":"webgpu:api/validation/createBindGroupLayout:max_resources_per_stage/in_bind_group_layout={\"maxedType\":\"readonly-storage-buffer\",\"maxedVisibility\":1,\"extraType\":\"sampler\",\"extraVisibility\":1}","status":"FAIL"},{"name":"webgpu:api/validation/createBindGroupLayout:max_resources_per_stage/in_bind_group_layout={\"maxedType\":\"readonly-storage-buffer\",\"maxedVisibility\":1,\"extraType\":\"sampler\",\"extraVisibility\":2}","status":"FAIL"},{"name":"webgpu:api/validation/createBindGroupLayout:max_resources_per_stage/in_bind_group_layout={\"maxedType\":\"readonly-storage-buffer\",\"maxedVisibility\":1,\"extraType\":\"sampler\",\"extraVisibility\":4}","status":"FAIL"},{"name":"webgpu:api/validation/createBindGroupLayout:max_resources_per_stage/in_bind_group_layout={\"maxedType\":\"readonly-storage-buffer\",\"maxedVisibility\":2,\"extraType\":\"storage-buffer\",\"extraVisibility\":4}","status":"FAIL"},{"name":"webgpu:api/validation/createBindGroupLayout:max_resources_per_stage/in_bind_group_layout={\"maxedType\":\"readonly-storage-buffer\",\"maxedVisibility\":2,\"extraType\":\"readonly-storage-buffer\",\"extraVisibility\":1}","status":"FAIL"},{"name":"webgpu:api/validation/createBindGroupLayout:max_resources_per_stage/in_bind_group_layout={\"maxedType\":\"readonly-storage-buffer\",\"maxedVisibility\":2,\"extraType\":\"readonly-storage-buffer\",\"extraVisibility\":2}","status":"FAIL"},{"name":"webgpu:api/validation/createBindGroupLayout:max_resources_per_stage/in_bind_group_layout={\"maxedType\":\"readonly-storage-buffer\",\"maxedVisibility\":2,\"extraType\":\"readonly-storage-buffer\",\"extraVisibility\":4}","status":"FAIL"},{"name":"webgpu:api/validation/createBindGroupLayout:max_resources_per_stage/in_bind_group_layout={\"maxedType\":\"readonly-storage-buffer\",\"maxedVisibility\":2,\"extraType\":\"sampler\",\"extraVisibility\":1}","status":"FAIL"},{"name":"webgpu:api/validation/createBindGroupLayout:max_resources_per_stage/in_bind_group_layout={\"maxedType\":\"readonly-storage-buffer\",\"maxedVisibility\":2,\"extraType\":\"sampler\",\"extraVisibility\":2}","status":"FAIL"},{"name":"webgpu:api/validation/createBindGroupLayout:max_resources_per_stage/in_bind_group_layout={\"maxedType\":\"readonly-storage-buffer\",\"maxedVisibility\":2,\"extraType\":\"sampler\",\"extraVisibility\":4}","status":"FAIL"},{"name":"webgpu:api/validation/createBindGroupLayout:max_resources_per_stage/in_bind_group_layout={\"maxedType\":\"readonly-storage-buffer\",\"maxedVisibility\":4,\"extraType\":\"storage-buffer\",\"extraVisibility\":4}","status":"FAIL"},{"name":"webgpu:api/validation/createBindGroupLayout:max_resources_per_stage/in_bind_group_layout={\"maxedType\":\"readonly-storage-buffer\",\"maxedVisibility\":4,\"extraType\":\"readonly-storage-buffer\",\"extraVisibility\":1}","status":"FAIL"},{"name":"webgpu:api/validation/createBindGroupLayout:max_resources_per_stage/in_bind_group_layout={\"maxedType\":\"readonly-storage-buffer\",\"maxedVisibility\":4,\"extraType\":\"readonly-storage-buffer\",\"extraVisibility\":2}","status":"FAIL"},{"name":"webgpu:api/validation/createBindGroupLayout:max_resources_per_stage/in_bind_group_layout={\"maxedType\":\"readonly-storage-buffer\",\"maxedVisibility\":4,\"extraType\":\"readonly-storage-buffer\",\"extraVisibility\":4}","status":"FAIL"},{"name":"webgpu:api/validation/createBindGroupLayout:max_resources_per_stage/in_bind_group_layout={\"maxedType\":\"readonly-storage-buffer\",\"maxedVisibility\":4,\"extraType\":\"sampler\",\"extraVisibility\":1}","status":"FAIL"},{"name":"webgpu:api/validation/createBindGroupLayout:max_resources_per_stage/in_bind_group_layout={\"maxedType\":\"readonly-storage-buffer\",\"maxedVisibility\":4,\"extraType\":\"sampler\",\"extraVisibility\":2}","status":"FAIL"},{"name":"webgpu:api/validation/createBindGroupLayout:max_resources_per_stage/in_bind_group_layout={\"maxedType\":\"readonly-storage-buffer\",\"maxedVisibility\":4,\"extraType\":\"sampler\",\"extraVisibility\":4}","status":"FAIL"},{"name":"webgpu:api/validation/createBindGroupLayout:max_resources_per_stage/in_bind_group_layout={\"maxedType\":\"sampler\",\"maxedVisibility\":1,\"extraType\":\"sampler\",\"extraVisibility\":1}","status":"FAIL"},{"name":"webgpu:api/validation/createBindGroupLayout:max_resources_per_stage/in_bind_group_layout={\"maxedType\":\"sampler\",\"maxedVisibility\":1,\"extraType\":\"sampler\",\"extraVisibility\":2}","status":"FAIL"},{"name":"webgpu:api/validation/createBindGroupLayout:max_resources_per_stage/in_bind_group_layout={\"maxedType\":\"sampler\",\"maxedVisibility\":1,\"extraType\":\"sampler\",\"extraVisibility\":4}","status":"FAIL"},{"name":"webgpu:api/validation/createBindGroupLayout:max_resources_per_stage/in_bind_group_layout={\"maxedType\":\"sampler\",\"maxedVisibility\":1,\"extraType\":\"comparison-sampler\",\"extraVisibility\":1}","status":"FAIL"},{"name":"webgpu:api/validation/createBindGroupLayout:max_resources_per_stage/in_bind_group_layout={\"maxedType\":\"sampler\",\"maxedVisibility\":1,\"extraType\":\"comparison-sampler\",\"extraVisibility\":2}","status":"FAIL"},{"name":"webgpu:api/validation/createBindGroupLayout:max_resources_per_stage/in_bind_group_layout={\"maxedType\":\"sampler\",\"maxedVisibility\":1,\"extraType\":\"comparison-sampler\",\"extraVisibility\":4}","status":"FAIL"},{"name":"webgpu:api/validation/createBindGroupLayout:max_resources_per_stage/in_bind_group_layout={\"maxedType\":\"sampler\",\"maxedVisibility\":1,\"extraType\":\"sampled-texture\",\"extraVisibility\":1}","status":"FAIL"},{"name":"webgpu:api/validation/createBindGroupLayout:max_resources_per_stage/in_bind_group_layout={\"maxedType\":\"sampler\",\"maxedVisibility\":1,\"extraType\":\"sampled-texture\",\"extraVisibility\":2}","status":"FAIL"},{"name":"webgpu:api/validation/createBindGroupLayout:max_resources_per_stage/in_bind_group_layout={\"maxedType\":\"sampler\",\"maxedVisibility\":1,\"extraType\":\"sampled-texture\",\"extraVisibility\":4}","status":"FAIL"},{"name":"webgpu:api/validation/createBindGroupLayout:max_resources_per_stage/in_bind_group_layout={\"maxedType\":\"sampler\",\"maxedVisibility\":2,\"extraType\":\"sampler\",\"extraVisibility\":1}","status":"FAIL"},{"name":"webgpu:api/validation/createBindGroupLayout:max_resources_per_stage/in_bind_group_layout={\"maxedType\":\"sampler\",\"maxedVisibility\":2,\"extraType\":\"sampler\",\"extraVisibility\":2}","status":"FAIL"},{"name":"webgpu:api/validation/createBindGroupLayout:max_resources_per_stage/in_bind_group_layout={\"maxedType\":\"sampler\",\"maxedVisibility\":2,\"extraType\":\"sampler\",\"extraVisibility\":4}","status":"FAIL"},{"name":"webgpu:api/validation/createBindGroupLayout:max_resources_per_stage/in_bind_group_layout={\"maxedType\":\"sampler\",\"maxedVisibility\":2,\"extraType\":\"comparison-sampler\",\"extraVisibility\":1}","status":"FAIL"},{"name":"webgpu:api/validation/createBindGroupLayout:max_resources_per_stage/in_bind_group_layout={\"maxedType\":\"sampler\",\"maxedVisibility\":2,\"extraType\":\"comparison-sampler\",\"extraVisibility\":2}","status":"FAIL"},{"name":"webgpu:api/validation/createBindGroupLayout:max_resources_per_stage/in_bind_group_layout={\"maxedType\":\"sampler\",\"maxedVisibility\":2,\"extraType\":\"comparison-sampler\",\"extraVisibility\":4}","status":"FAIL"},{"name":"webgpu:api/validation/createBindGroupLayout:max_resources_per_stage/in_bind_group_layout={\"maxedType\":\"sampler\",\"maxedVisibility\":2,\"extraType\":\"sampled-texture\",\"extraVisibility\":1}","status":"FAIL"},{"name":"webgpu:api/validation/createBindGroupLayout:max_resources_per_stage/in_bind_group_layout={\"maxedType\":\"sampler\",\"maxedVisibility\":2,\"extraType\":\"sampled-texture\",\"extraVisibility\":2}","status":"FAIL"},{"name":"webgpu:api/validation/createBindGroupLayout:max_resources_per_stage/in_bind_group_layout={\"maxedType\":\"sampler\",\"maxedVisibility\":2,\"extraType\":\"sampled-texture\",\"extraVisibility\":4}","status":"FAIL"},{"name":"webgpu:api/validation/createBindGroupLayout:max_resources_per_stage/in_bind_group_layout={\"maxedType\":\"sampler\",\"maxedVisibility\":4,\"extraType\":\"sampler\",\"extraVisibility\":1}","status":"FAIL"},{"name":"webgpu:api/validation/createBindGroupLayout:max_resources_per_stage/in_bind_group_layout={\"maxedType\":\"sampler\",\"maxedVisibility\":4,\"extraType\":\"sampler\",\"extraVisibility\":2}","status":"FAIL"},{"name":"webgpu:api/validation/createBindGroupLayout:max_resources_per_stage/in_bind_group_layout={\"maxedType\":\"sampler\",\"maxedVisibility\":4,\"extraType\":\"sampler\",\"extraVisibility\":4}","status":"FAIL"},{"name":"webgpu:api/validation/createBindGroupLayout:max_resources_per_stage/in_bind_group_layout={\"maxedType\":\"sampler\",\"maxedVisibility\":4,\"extraType\":\"comparison-sampler\",\"extraVisibility\":1}","status":"FAIL"},{"name":"webgpu:api/validation/createBindGroupLayout:max_resources_per_stage/in_bind_group_layout={\"maxedType\":\"sampler\",\"maxedVisibility\":4,\"extraType\":\"comparison-sampler\",\"extraVisibility\":2}","status":"FAIL"},{"name":"webgpu:api/validation/createBindGroupLayout:max_resources_per_stage/in_bind_group_layout={\"maxedType\":\"sampler\",\"maxedVisibility\":4,\"extraType\":\"comparison-sampler\",\"extraVisibility\":4}","status":"FAIL"},{"name":"webgpu:api/validation/createBindGroupLayout:max_resources_per_stage/in_bind_group_layout={\"maxedType\":\"sampler\",\"maxedVisibility\":4,\"extraType\":\"sampled-texture\",\"extraVisibility\":1}","status":"FAIL"},{"name":"webgpu:api/validation/createBindGroupLayout:max_resources_per_stage/in_bind_group_layout={\"maxedType\":\"sampler\",\"maxedVisibility\":4,\"extraType\":\"sampled-texture\",\"extraVisibility\":2}","status":"FAIL"},{"name":"webgpu:api/validation/createBindGroupLayout:max_resources_per_stage/in_bind_group_layout={\"maxedType\":\"sampler\",\"maxedVisibility\":4,\"extraType\":\"sampled-texture\",\"extraVisibility\":4}","status":"FAIL"},{"name":"webgpu:api/validation/createBindGroupLayout:max_resources_per_stage/in_bind_group_layout={\"maxedType\":\"comparison-sampler\",\"maxedVisibility\":1,\"extraType\":\"sampler\",\"extraVisibility\":1}","status":"FAIL"},{"name":"webgpu:api/validation/createBindGroupLayout:max_resources_per_stage/in_bind_group_layout={\"maxedType\":\"comparison-sampler\",\"maxedVisibility\":1,\"extraType\":\"sampler\",\"extraVisibility\":2}","status":"FAIL"},{"name":"webgpu:api/validation/createBindGroupLayout:max_resources_per_stage/in_bind_group_layout={\"maxedType\":\"comparison-sampler\",\"maxedVisibility\":1,\"extraType\":\"sampler\",\"extraVisibility\":4}","status":"FAIL"},{"name":"webgpu:api/validation/createBindGroupLayout:max_resources_per_stage/in_bind_group_layout={\"maxedType\":\"comparison-sampler\",\"maxedVisibility\":1,\"extraType\":\"comparison-sampler\",\"extraVisibility\":1}","status":"FAIL"},{"name":"webgpu:api/validation/createBindGroupLayout:max_resources_per_stage/in_bind_group_layout={\"maxedType\":\"comparison-sampler\",\"maxedVisibility\":1,\"extraType\":\"comparison-sampler\",\"extraVisibility\":2}","status":"FAIL"},{"name":"webgpu:api/validation/createBindGroupLayout:max_resources_per_stage/in_bind_group_layout={\"maxedType\":\"comparison-sampler\",\"maxedVisibility\":1,\"extraType\":\"comparison-sampler\",\"extraVisibility\":4}","status":"FAIL"},{"name":"webgpu:api/validation/createBindGroupLayout:max_resources_per_stage/in_bind_group_layout={\"maxedType\":\"comparison-sampler\",\"maxedVisibility\":1,\"extraType\":\"sampled-texture\",\"extraVisibility\":1}","status":"FAIL"},{"name":"webgpu:api/validation/createBindGroupLayout:max_resources_per_stage/in_bind_group_layout={\"maxedType\":\"comparison-sampler\",\"maxedVisibility\":1,\"extraType\":\"sampled-texture\",\"extraVisibility\":2}","status":"FAIL"},{"name":"webgpu:api/validation/createBindGroupLayout:max_resources_per_stage/in_bind_group_layout={\"maxedType\":\"comparison-sampler\",\"maxedVisibility\":1,\"extraType\":\"sampled-texture\",\"extraVisibility\":4}","status":"FAIL"},{"name":"webgpu:api/validation/createBindGroupLayout:max_resources_per_stage/in_bind_group_layout={\"maxedType\":\"comparison-sampler\",\"maxedVisibility\":2,\"extraType\":\"sampler\",\"extraVisibility\":1}","status":"FAIL"},{"name":"webgpu:api/validation/createBindGroupLayout:max_resources_per_stage/in_bind_group_layout={\"maxedType\":\"comparison-sampler\",\"maxedVisibility\":2,\"extraType\":\"sampler\",\"extraVisibility\":2}","status":"FAIL"},{"name":"webgpu:api/validation/createBindGroupLayout:max_resources_per_stage/in_bind_group_layout={\"maxedType\":\"comparison-sampler\",\"maxedVisibility\":2,\"extraType\":\"sampler\",\"extraVisibility\":4}","status":"FAIL"},{"name":"webgpu:api/validation/createBindGroupLayout:max_resources_per_stage/in_bind_group_layout={\"maxedType\":\"comparison-sampler\",\"maxedVisibility\":2,\"extraType\":\"comparison-sampler\",\"extraVisibility\":1}","status":"FAIL"},{"name":"webgpu:api/validation/createBindGroupLayout:max_resources_per_stage/in_bind_group_layout={\"maxedType\":\"comparison-sampler\",\"maxedVisibility\":2,\"extraType\":\"comparison-sampler\",\"extraVisibility\":2}","status":"FAIL"},{"name":"webgpu:api/validation/createBindGroupLayout:max_resources_per_stage/in_bind_group_layout={\"maxedType\":\"comparison-sampler\",\"maxedVisibility\":2,\"extraType\":\"comparison-sampler\",\"extraVisibility\":4}","status":"FAIL"},{"name":"webgpu:api/validation/createBindGroupLayout:max_resources_per_stage/in_bind_group_layout={\"maxedType\":\"comparison-sampler\",\"maxedVisibility\":2,\"extraType\":\"sampled-texture\",\"extraVisibility\":1}","status":"FAIL"},{"name":"webgpu:api/validation/createBindGroupLayout:max_resources_per_stage/in_bind_group_layout={\"maxedType\":\"comparison-sampler\",\"maxedVisibility\":2,\"extraType\":\"sampled-texture\",\"extraVisibility\":2}","status":"FAIL"},{"name":"webgpu:api/validation/createBindGroupLayout:max_resources_per_stage/in_bind_group_layout={\"maxedType\":\"comparison-sampler\",\"maxedVisibility\":2,\"extraType\":\"sampled-texture\",\"extraVisibility\":4}","status":"FAIL"},{"name":"webgpu:api/validation/createBindGroupLayout:max_resources_per_stage/in_bind_group_layout={\"maxedType\":\"comparison-sampler\",\"maxedVisibility\":4,\"extraType\":\"sampler\",\"extraVisibility\":1}","status":"FAIL"},{"name":"webgpu:api/validation/createBindGroupLayout:max_resources_per_stage/in_bind_group_layout={\"maxedType\":\"comparison-sampler\",\"maxedVisibility\":4,\"extraType\":\"sampler\",\"extraVisibility\":2}","status":"FAIL"},{"name":"webgpu:api/validation/createBindGroupLayout:max_resources_per_stage/in_bind_group_layout={\"maxedType\":\"comparison-sampler\",\"maxedVisibility\":4,\"extraType\":\"sampler\",\"extraVisibility\":4}","status":"FAIL"},{"name":"webgpu:api/validation/createBindGroupLayout:max_resources_per_stage/in_bind_group_layout={\"maxedType\":\"comparison-sampler\",\"maxedVisibility\":4,\"extraType\":\"comparison-sampler\",\"extraVisibility\":1}","status":"FAIL"},{"name":"webgpu:api/validation/createBindGroupLayout:max_resources_per_stage/in_bind_group_layout={\"maxedType\":\"comparison-sampler\",\"maxedVisibility\":4,\"extraType\":\"comparison-sampler\",\"extraVisibility\":2}","status":"FAIL"},{"name":"webgpu:api/validation/createBindGroupLayout:max_resources_per_stage/in_bind_group_layout={\"maxedType\":\"comparison-sampler\",\"maxedVisibility\":4,\"extraType\":\"comparison-sampler\",\"extraVisibility\":4}","status":"FAIL"},{"name":"webgpu:api/validation/createBindGroupLayout:max_resources_per_stage/in_bind_group_layout={\"maxedType\":\"comparison-sampler\",\"maxedVisibility\":4,\"extraType\":\"sampled-texture\",\"extraVisibility\":1}","status":"FAIL"},{"name":"webgpu:api/validation/createBindGroupLayout:max_resources_per_stage/in_bind_group_layout={\"maxedType\":\"comparison-sampler\",\"maxedVisibility\":4,\"extraType\":\"sampled-texture\",\"extraVisibility\":2}","status":"FAIL"},{"name":"webgpu:api/validation/createBindGroupLayout:max_resources_per_stage/in_bind_group_layout={\"maxedType\":\"comparison-sampler\",\"maxedVisibility\":4,\"extraType\":\"sampled-texture\",\"extraVisibility\":4}","status":"FAIL"},{"name":"webgpu:api/validation/createBindGroupLayout:max_resources_per_stage/in_bind_group_layout={\"maxedType\":\"sampled-texture\",\"maxedVisibility\":1,\"extraType\":\"sampled-texture\",\"extraVisibility\":1}","status":"FAIL"},{"name":"webgpu:api/validation/createBindGroupLayout:max_resources_per_stage/in_bind_group_layout={\"maxedType\":\"sampled-texture\",\"maxedVisibility\":1,\"extraType\":\"sampled-texture\",\"extraVisibility\":2}","status":"FAIL"},{"name":"webgpu:api/validation/createBindGroupLayout:max_resources_per_stage/in_bind_group_layout={\"maxedType\":\"sampled-texture\",\"maxedVisibility\":1,\"extraType\":\"sampled-texture\",\"extraVisibility\":4}","status":"FAIL"},{"name":"webgpu:api/validation/createBindGroupLayout:max_resources_per_stage/in_bind_group_layout={\"maxedType\":\"sampled-texture\",\"maxedVisibility\":1,\"extraType\":\"sampler\",\"extraVisibility\":1}","status":"FAIL"},{"name":"webgpu:api/validation/createBindGroupLayout:max_resources_per_stage/in_bind_group_layout={\"maxedType\":\"sampled-texture\",\"maxedVisibility\":1,\"extraType\":\"sampler\",\"extraVisibility\":2}","status":"FAIL"},{"name":"webgpu:api/validation/createBindGroupLayout:max_resources_per_stage/in_bind_group_layout={\"maxedType\":\"sampled-texture\",\"maxedVisibility\":1,\"extraType\":\"sampler\",\"extraVisibility\":4}","status":"FAIL"},{"name":"webgpu:api/validation/createBindGroupLayout:max_resources_per_stage/in_bind_group_layout={\"maxedType\":\"sampled-texture\",\"maxedVisibility\":2,\"extraType\":\"sampled-texture\",\"extraVisibility\":1}","status":"FAIL"},{"name":"webgpu:api/validation/createBindGroupLayout:max_resources_per_stage/in_bind_group_layout={\"maxedType\":\"sampled-texture\",\"maxedVisibility\":2,\"extraType\":\"sampled-texture\",\"extraVisibility\":2}","status":"FAIL"},{"name":"webgpu:api/validation/createBindGroupLayout:max_resources_per_stage/in_bind_group_layout={\"maxedType\":\"sampled-texture\",\"maxedVisibility\":2,\"extraType\":\"sampled-texture\",\"extraVisibility\":4}","status":"FAIL"},{"name":"webgpu:api/validation/createBindGroupLayout:max_resources_per_stage/in_bind_group_layout={\"maxedType\":\"sampled-texture\",\"maxedVisibility\":2,\"extraType\":\"sampler\",\"extraVisibility\":1}","status":"FAIL"},{"name":"webgpu:api/validation/createBindGroupLayout:max_resources_per_stage/in_bind_group_layout={\"maxedType\":\"sampled-texture\",\"maxedVisibility\":2,\"extraType\":\"sampler\",\"extraVisibility\":2}","status":"FAIL"},{"name":"webgpu:api/validation/createBindGroupLayout:max_resources_per_stage/in_bind_group_layout={\"maxedType\":\"sampled-texture\",\"maxedVisibility\":2,\"extraType\":\"sampler\",\"extraVisibility\":4}","status":"FAIL"},{"name":"webgpu:api/validation/createBindGroupLayout:max_resources_per_stage/in_bind_group_layout={\"maxedType\":\"sampled-texture\",\"maxedVisibility\":4,\"extraType\":\"sampled-texture\",\"extraVisibility\":1}","status":"FAIL"},{"name":"webgpu:api/validation/createBindGroupLayout:max_resources_per_stage/in_bind_group_layout={\"maxedType\":\"sampled-texture\",\"maxedVisibility\":4,\"extraType\":\"sampled-texture\",\"extraVisibility\":2}","status":"FAIL"},{"name":"webgpu:api/validation/createBindGroupLayout:max_resources_per_stage/in_bind_group_layout={\"maxedType\":\"sampled-texture\",\"maxedVisibility\":4,\"extraType\":\"sampled-texture\",\"extraVisibility\":4}","status":"FAIL"},{"name":"webgpu:api/validation/createBindGroupLayout:max_resources_per_stage/in_bind_group_layout={\"maxedType\":\"sampled-texture\",\"maxedVisibility\":4,\"extraType\":\"sampler\",\"extraVisibility\":1}","status":"FAIL"},{"name":"webgpu:api/validation/createBindGroupLayout:max_resources_per_stage/in_bind_group_layout={\"maxedType\":\"sampled-texture\",\"maxedVisibility\":4,\"extraType\":\"sampler\",\"extraVisibility\":2}","status":"FAIL"},{"name":"webgpu:api/validation/createBindGroupLayout:max_resources_per_stage/in_bind_group_layout={\"maxedType\":\"sampled-texture\",\"maxedVisibility\":4,\"extraType\":\"sampler\",\"extraVisibility\":4}","status":"FAIL"},{"name":"webgpu:api/validation/createBindGroupLayout:max_resources_per_stage/in_bind_group_layout={\"maxedType\":\"writeonly-storage-texture\",\"maxedVisibility\":4,\"extraType\":\"writeonly-storage-texture\",\"extraVisibility\":4}","status":"FAIL"},{"name":"webgpu:api/validation/createBindGroupLayout:max_resources_per_stage/in_bind_group_layout={\"maxedType\":\"writeonly-storage-texture\",\"maxedVisibility\":4,\"extraType\":\"readonly-storage-texture\",\"extraVisibility\":1}","status":"FAIL"},{"name":"webgpu:api/validation/createBindGroupLayout:max_resources_per_stage/in_bind_group_layout={\"maxedType\":\"writeonly-storage-texture\",\"maxedVisibility\":4,\"extraType\":\"readonly-storage-texture\",\"extraVisibility\":2}","status":"FAIL"},{"name":"webgpu:api/validation/createBindGroupLayout:max_resources_per_stage/in_bind_group_layout={\"maxedType\":\"writeonly-storage-texture\",\"maxedVisibility\":4,\"extraType\":\"readonly-storage-texture\",\"extraVisibility\":4}","status":"FAIL"},{"name":"webgpu:api/validation/createBindGroupLayout:max_resources_per_stage/in_bind_group_layout={\"maxedType\":\"writeonly-storage-texture\",\"maxedVisibility\":4,\"extraType\":\"sampler\",\"extraVisibility\":1}","status":"FAIL"},{"name":"webgpu:api/validation/createBindGroupLayout:max_resources_per_stage/in_bind_group_layout={\"maxedType\":\"writeonly-storage-texture\",\"maxedVisibility\":4,\"extraType\":\"sampler\",\"extraVisibility\":2}","status":"FAIL"},{"name":"webgpu:api/validation/createBindGroupLayout:max_resources_per_stage/in_bind_group_layout={\"maxedType\":\"writeonly-storage-texture\",\"maxedVisibility\":4,\"extraType\":\"sampler\",\"extraVisibility\":4}","status":"FAIL"},{"name":"webgpu:api/validation/createBindGroupLayout:max_resources_per_stage/in_bind_group_layout={\"maxedType\":\"readonly-storage-texture\",\"maxedVisibility\":1,\"extraType\":\"writeonly-storage-texture\",\"extraVisibility\":4}","status":"FAIL"},{"name":"webgpu:api/validation/createBindGroupLayout:max_resources_per_stage/in_bind_group_layout={\"maxedType\":\"readonly-storage-texture\",\"maxedVisibility\":1,\"extraType\":\"readonly-storage-texture\",\"extraVisibility\":1}","status":"FAIL"},{"name":"webgpu:api/validation/createBindGroupLayout:max_resources_per_stage/in_bind_group_layout={\"maxedType\":\"readonly-storage-texture\",\"maxedVisibility\":1,\"extraType\":\"readonly-storage-texture\",\"extraVisibility\":2}","status":"FAIL"},{"name":"webgpu:api/validation/createBindGroupLayout:max_resources_per_stage/in_bind_group_layout={\"maxedType\":\"readonly-storage-texture\",\"maxedVisibility\":1,\"extraType\":\"readonly-storage-texture\",\"extraVisibility\":4}","status":"FAIL"},{"name":"webgpu:api/validation/createBindGroupLayout:max_resources_per_stage/in_bind_group_layout={\"maxedType\":\"readonly-storage-texture\",\"maxedVisibility\":1,\"extraType\":\"sampler\",\"extraVisibility\":1}","status":"FAIL"},{"name":"webgpu:api/validation/createBindGroupLayout:max_resources_per_stage/in_bind_group_layout={\"maxedType\":\"readonly-storage-texture\",\"maxedVisibility\":1,\"extraType\":\"sampler\",\"extraVisibility\":2}","status":"FAIL"},{"name":"webgpu:api/validation/createBindGroupLayout:max_resources_per_stage/in_bind_group_layout={\"maxedType\":\"readonly-storage-texture\",\"maxedVisibility\":1,\"extraType\":\"sampler\",\"extraVisibility\":4}","status":"FAIL"},{"name":"webgpu:api/validation/createBindGroupLayout:max_resources_per_stage/in_bind_group_layout={\"maxedType\":\"readonly-storage-texture\",\"maxedVisibility\":2,\"extraType\":\"writeonly-storage-texture\",\"extraVisibility\":4}","status":"FAIL"},{"name":"webgpu:api/validation/createBindGroupLayout:max_resources_per_stage/in_bind_group_layout={\"maxedType\":\"readonly-storage-texture\",\"maxedVisibility\":2,\"extraType\":\"readonly-storage-texture\",\"extraVisibility\":1}","status":"FAIL"},{"name":"webgpu:api/validation/createBindGroupLayout:max_resources_per_stage/in_bind_group_layout={\"maxedType\":\"readonly-storage-texture\",\"maxedVisibility\":2,\"extraType\":\"readonly-storage-texture\",\"extraVisibility\":2}","status":"FAIL"},{"name":"webgpu:api/validation/createBindGroupLayout:max_resources_per_stage/in_bind_group_layout={\"maxedType\":\"readonly-storage-texture\",\"maxedVisibility\":2,\"extraType\":\"readonly-storage-texture\",\"extraVisibility\":4}","status":"FAIL"},{"name":"webgpu:api/validation/createBindGroupLayout:max_resources_per_stage/in_bind_group_layout={\"maxedType\":\"readonly-storage-texture\",\"maxedVisibility\":2,\"extraType\":\"sampler\",\"extraVisibility\":1}","status":"FAIL"},{"name":"webgpu:api/validation/createBindGroupLayout:max_resources_per_stage/in_bind_group_layout={\"maxedType\":\"readonly-storage-texture\",\"maxedVisibility\":2,\"extraType\":\"sampler\",\"extraVisibility\":2}","status":"FAIL"},{"name":"webgpu:api/validation/createBindGroupLayout:max_resources_per_stage/in_bind_group_layout={\"maxedType\":\"readonly-storage-texture\",\"maxedVisibility\":2,\"extraType\":\"sampler\",\"extraVisibility\":4}","status":"FAIL"},{"name":"webgpu:api/validation/createBindGroupLayout:max_resources_per_stage/in_bind_group_layout={\"maxedType\":\"readonly-storage-texture\",\"maxedVisibility\":4,\"extraType\":\"writeonly-storage-texture\",\"extraVisibility\":4}","status":"FAIL"},{"name":"webgpu:api/validation/createBindGroupLayout:max_resources_per_stage/in_bind_group_layout={\"maxedType\":\"readonly-storage-texture\",\"maxedVisibility\":4,\"extraType\":\"readonly-storage-texture\",\"extraVisibility\":1}","status":"FAIL"},{"name":"webgpu:api/validation/createBindGroupLayout:max_resources_per_stage/in_bind_group_layout={\"maxedType\":\"readonly-storage-texture\",\"maxedVisibility\":4,\"extraType\":\"readonly-storage-texture\",\"extraVisibility\":2}","status":"FAIL"},{"name":"webgpu:api/validation/createBindGroupLayout:max_resources_per_stage/in_bind_group_layout={\"maxedType\":\"readonly-storage-texture\",\"maxedVisibility\":4,\"extraType\":\"readonly-storage-texture\",\"extraVisibility\":4}","status":"FAIL"},{"name":"webgpu:api/validation/createBindGroupLayout:max_resources_per_stage/in_bind_group_layout={\"maxedType\":\"readonly-storage-texture\",\"maxedVisibility\":4,\"extraType\":\"sampler\",\"extraVisibility\":1}","status":"FAIL"},{"name":"webgpu:api/validation/createBindGroupLayout:max_resources_per_stage/in_bind_group_layout={\"maxedType\":\"readonly-storage-texture\",\"maxedVisibility\":4,\"extraType\":\"sampler\",\"extraVisibility\":2}","status":"FAIL"},{"name":"webgpu:api/validation/createBindGroupLayout:max_resources_per_stage/in_bind_group_layout={\"maxedType\":\"readonly-storage-texture\",\"maxedVisibility\":4,\"extraType\":\"sampler\",\"extraVisibility\":4}","status":"FAIL"},{"name":"webgpu:api/validation/createBindGroupLayout:max_resources_per_stage/in_pipeline_layout={\"maxedType\":\"uniform-buffer\",\"maxedVisibility\":1,\"extraType\":\"uniform-buffer\",\"extraVisibility\":1}","status":"FAIL"},{"name":"webgpu:api/validation/createBindGroupLayout:max_resources_per_stage/in_pipeline_layout={\"maxedType\":\"uniform-buffer\",\"maxedVisibility\":1,\"extraType\":\"uniform-buffer\",\"extraVisibility\":2}","status":"FAIL"},{"name":"webgpu:api/validation/createBindGroupLayout:max_resources_per_stage/in_pipeline_layout={\"maxedType\":\"uniform-buffer\",\"maxedVisibility\":1,\"extraType\":\"uniform-buffer\",\"extraVisibility\":4}","status":"FAIL"},{"name":"webgpu:api/validation/createBindGroupLayout:max_resources_per_stage/in_pipeline_layout={\"maxedType\":\"uniform-buffer\",\"maxedVisibility\":1,\"extraType\":\"sampler\",\"extraVisibility\":1}","status":"FAIL"},{"name":"webgpu:api/validation/createBindGroupLayout:max_resources_per_stage/in_pipeline_layout={\"maxedType\":\"uniform-buffer\",\"maxedVisibility\":1,\"extraType\":\"sampler\",\"extraVisibility\":2}","status":"FAIL"},{"name":"webgpu:api/validation/createBindGroupLayout:max_resources_per_stage/in_pipeline_layout={\"maxedType\":\"uniform-buffer\",\"maxedVisibility\":1,\"extraType\":\"sampler\",\"extraVisibility\":4}","status":"FAIL"},{"name":"webgpu:api/validation/createBindGroupLayout:max_resources_per_stage/in_pipeline_layout={\"maxedType\":\"uniform-buffer\",\"maxedVisibility\":2,\"extraType\":\"uniform-buffer\",\"extraVisibility\":1}","status":"FAIL"},{"name":"webgpu:api/validation/createBindGroupLayout:max_resources_per_stage/in_pipeline_layout={\"maxedType\":\"uniform-buffer\",\"maxedVisibility\":2,\"extraType\":\"uniform-buffer\",\"extraVisibility\":2}","status":"FAIL"},{"name":"webgpu:api/validation/createBindGroupLayout:max_resources_per_stage/in_pipeline_layout={\"maxedType\":\"uniform-buffer\",\"maxedVisibility\":2,\"extraType\":\"uniform-buffer\",\"extraVisibility\":4}","status":"FAIL"},{"name":"webgpu:api/validation/createBindGroupLayout:max_resources_per_stage/in_pipeline_layout={\"maxedType\":\"uniform-buffer\",\"maxedVisibility\":2,\"extraType\":\"sampler\",\"extraVisibility\":1}","status":"FAIL"},{"name":"webgpu:api/validation/createBindGroupLayout:max_resources_per_stage/in_pipeline_layout={\"maxedType\":\"uniform-buffer\",\"maxedVisibility\":2,\"extraType\":\"sampler\",\"extraVisibility\":2}","status":"FAIL"},{"name":"webgpu:api/validation/createBindGroupLayout:max_resources_per_stage/in_pipeline_layout={\"maxedType\":\"uniform-buffer\",\"maxedVisibility\":2,\"extraType\":\"sampler\",\"extraVisibility\":4}","status":"FAIL"},{"name":"webgpu:api/validation/createBindGroupLayout:max_resources_per_stage/in_pipeline_layout={\"maxedType\":\"uniform-buffer\",\"maxedVisibility\":4,\"extraType\":\"uniform-buffer\",\"extraVisibility\":1}","status":"FAIL"},{"name":"webgpu:api/validation/createBindGroupLayout:max_resources_per_stage/in_pipeline_layout={\"maxedType\":\"uniform-buffer\",\"maxedVisibility\":4,\"extraType\":\"uniform-buffer\",\"extraVisibility\":2}","status":"FAIL"},{"name":"webgpu:api/validation/createBindGroupLayout:max_resources_per_stage/in_pipeline_layout={\"maxedType\":\"uniform-buffer\",\"maxedVisibility\":4,\"extraType\":\"uniform-buffer\",\"extraVisibility\":4}","status":"FAIL"},{"name":"webgpu:api/validation/createBindGroupLayout:max_resources_per_stage/in_pipeline_layout={\"maxedType\":\"uniform-buffer\",\"maxedVisibility\":4,\"extraType\":\"sampler\",\"extraVisibility\":1}","status":"FAIL"},{"name":"webgpu:api/validation/createBindGroupLayout:max_resources_per_stage/in_pipeline_layout={\"maxedType\":\"uniform-buffer\",\"maxedVisibility\":4,\"extraType\":\"sampler\",\"extraVisibility\":2}","status":"FAIL"},{"name":"webgpu:api/validation/createBindGroupLayout:max_resources_per_stage/in_pipeline_layout={\"maxedType\":\"uniform-buffer\",\"maxedVisibility\":4,\"extraType\":\"sampler\",\"extraVisibility\":4}","status":"FAIL"},{"name":"webgpu:api/validation/createBindGroupLayout:max_resources_per_stage/in_pipeline_layout={\"maxedType\":\"storage-buffer\",\"maxedVisibility\":4,\"extraType\":\"storage-buffer\",\"extraVisibility\":4}","status":"FAIL"},{"name":"webgpu:api/validation/createBindGroupLayout:max_resources_per_stage/in_pipeline_layout={\"maxedType\":\"storage-buffer\",\"maxedVisibility\":4,\"extraType\":\"readonly-storage-buffer\",\"extraVisibility\":1}","status":"FAIL"},{"name":"webgpu:api/validation/createBindGroupLayout:max_resources_per_stage/in_pipeline_layout={\"maxedType\":\"storage-buffer\",\"maxedVisibility\":4,\"extraType\":\"readonly-storage-buffer\",\"extraVisibility\":2}","status":"FAIL"},{"name":"webgpu:api/validation/createBindGroupLayout:max_resources_per_stage/in_pipeline_layout={\"maxedType\":\"storage-buffer\",\"maxedVisibility\":4,\"extraType\":\"readonly-storage-buffer\",\"extraVisibility\":4}","status":"FAIL"},{"name":"webgpu:api/validation/createBindGroupLayout:max_resources_per_stage/in_pipeline_layout={\"maxedType\":\"storage-buffer\",\"maxedVisibility\":4,\"extraType\":\"sampler\",\"extraVisibility\":1}","status":"FAIL"},{"name":"webgpu:api/validation/createBindGroupLayout:max_resources_per_stage/in_pipeline_layout={\"maxedType\":\"storage-buffer\",\"maxedVisibility\":4,\"extraType\":\"sampler\",\"extraVisibility\":2}","status":"FAIL"},{"name":"webgpu:api/validation/createBindGroupLayout:max_resources_per_stage/in_pipeline_layout={\"maxedType\":\"storage-buffer\",\"maxedVisibility\":4,\"extraType\":\"sampler\",\"extraVisibility\":4}","status":"FAIL"},{"name":"webgpu:api/validation/createBindGroupLayout:max_resources_per_stage/in_pipeline_layout={\"maxedType\":\"readonly-storage-buffer\",\"maxedVisibility\":1,\"extraType\":\"storage-buffer\",\"extraVisibility\":4}","status":"FAIL"},{"name":"webgpu:api/validation/createBindGroupLayout:max_resources_per_stage/in_pipeline_layout={\"maxedType\":\"readonly-storage-buffer\",\"maxedVisibility\":1,\"extraType\":\"readonly-storage-buffer\",\"extraVisibility\":1}","status":"FAIL"},{"name":"webgpu:api/validation/createBindGroupLayout:max_resources_per_stage/in_pipeline_layout={\"maxedType\":\"readonly-storage-buffer\",\"maxedVisibility\":1,\"extraType\":\"readonly-storage-buffer\",\"extraVisibility\":2}","status":"FAIL"},{"name":"webgpu:api/validation/createBindGroupLayout:max_resources_per_stage/in_pipeline_layout={\"maxedType\":\"readonly-storage-buffer\",\"maxedVisibility\":1,\"extraType\":\"readonly-storage-buffer\",\"extraVisibility\":4}","status":"FAIL"},{"name":"webgpu:api/validation/createBindGroupLayout:max_resources_per_stage/in_pipeline_layout={\"maxedType\":\"readonly-storage-buffer\",\"maxedVisibility\":1,\"extraType\":\"sampler\",\"extraVisibility\":1}","status":"FAIL"},{"name":"webgpu:api/validation/createBindGroupLayout:max_resources_per_stage/in_pipeline_layout={\"maxedType\":\"readonly-storage-buffer\",\"maxedVisibility\":1,\"extraType\":\"sampler\",\"extraVisibility\":2}","status":"FAIL"},{"name":"webgpu:api/validation/createBindGroupLayout:max_resources_per_stage/in_pipeline_layout={\"maxedType\":\"readonly-storage-buffer\",\"maxedVisibility\":1,\"extraType\":\"sampler\",\"extraVisibility\":4}","status":"FAIL"},{"name":"webgpu:api/validation/createBindGroupLayout:max_resources_per_stage/in_pipeline_layout={\"maxedType\":\"readonly-storage-buffer\",\"maxedVisibility\":2,\"extraType\":\"storage-buffer\",\"extraVisibility\":4}","status":"FAIL"},{"name":"webgpu:api/validation/createBindGroupLayout:max_resources_per_stage/in_pipeline_layout={\"maxedType\":\"readonly-storage-buffer\",\"maxedVisibility\":2,\"extraType\":\"readonly-storage-buffer\",\"extraVisibility\":1}","status":"FAIL"},{"name":"webgpu:api/validation/createBindGroupLayout:max_resources_per_stage/in_pipeline_layout={\"maxedType\":\"readonly-storage-buffer\",\"maxedVisibility\":2,\"extraType\":\"readonly-storage-buffer\",\"extraVisibility\":2}","status":"FAIL"},{"name":"webgpu:api/validation/createBindGroupLayout:max_resources_per_stage/in_pipeline_layout={\"maxedType\":\"readonly-storage-buffer\",\"maxedVisibility\":2,\"extraType\":\"readonly-storage-buffer\",\"extraVisibility\":4}","status":"FAIL"},{"name":"webgpu:api/validation/createBindGroupLayout:max_resources_per_stage/in_pipeline_layout={\"maxedType\":\"readonly-storage-buffer\",\"maxedVisibility\":2,\"extraType\":\"sampler\",\"extraVisibility\":1}","status":"FAIL"},{"name":"webgpu:api/validation/createBindGroupLayout:max_resources_per_stage/in_pipeline_layout={\"maxedType\":\"readonly-storage-buffer\",\"maxedVisibility\":2,\"extraType\":\"sampler\",\"extraVisibility\":2}","status":"FAIL"},{"name":"webgpu:api/validation/createBindGroupLayout:max_resources_per_stage/in_pipeline_layout={\"maxedType\":\"readonly-storage-buffer\",\"maxedVisibility\":2,\"extraType\":\"sampler\",\"extraVisibility\":4}","status":"FAIL"},{"name":"webgpu:api/validation/createBindGroupLayout:max_resources_per_stage/in_pipeline_layout={\"maxedType\":\"readonly-storage-buffer\",\"maxedVisibility\":4,\"extraType\":\"storage-buffer\",\"extraVisibility\":4}","status":"FAIL"},{"name":"webgpu:api/validation/createBindGroupLayout:max_resources_per_stage/in_pipeline_layout={\"maxedType\":\"readonly-storage-buffer\",\"maxedVisibility\":4,\"extraType\":\"readonly-storage-buffer\",\"extraVisibility\":1}","status":"FAIL"},{"name":"webgpu:api/validation/createBindGroupLayout:max_resources_per_stage/in_pipeline_layout={\"maxedType\":\"readonly-storage-buffer\",\"maxedVisibility\":4,\"extraType\":\"readonly-storage-buffer\",\"extraVisibility\":2}","status":"FAIL"},{"name":"webgpu:api/validation/createBindGroupLayout:max_resources_per_stage/in_pipeline_layout={\"maxedType\":\"readonly-storage-buffer\",\"maxedVisibility\":4,\"extraType\":\"readonly-storage-buffer\",\"extraVisibility\":4}","status":"FAIL"},{"name":"webgpu:api/validation/createBindGroupLayout:max_resources_per_stage/in_pipeline_layout={\"maxedType\":\"readonly-storage-buffer\",\"maxedVisibility\":4,\"extraType\":\"sampler\",\"extraVisibility\":1}","status":"FAIL"},{"name":"webgpu:api/validation/createBindGroupLayout:max_resources_per_stage/in_pipeline_layout={\"maxedType\":\"readonly-storage-buffer\",\"maxedVisibility\":4,\"extraType\":\"sampler\",\"extraVisibility\":2}","status":"FAIL"},{"name":"webgpu:api/validation/createBindGroupLayout:max_resources_per_stage/in_pipeline_layout={\"maxedType\":\"readonly-storage-buffer\",\"maxedVisibility\":4,\"extraType\":\"sampler\",\"extraVisibility\":4}","status":"FAIL"},{"name":"webgpu:api/validation/createBindGroupLayout:max_resources_per_stage/in_pipeline_layout={\"maxedType\":\"sampler\",\"maxedVisibility\":1,\"extraType\":\"sampler\",\"extraVisibility\":1}","status":"FAIL"},{"name":"webgpu:api/validation/createBindGroupLayout:max_resources_per_stage/in_pipeline_layout={\"maxedType\":\"sampler\",\"maxedVisibility\":1,\"extraType\":\"sampler\",\"extraVisibility\":2}","status":"FAIL"},{"name":"webgpu:api/validation/createBindGroupLayout:max_resources_per_stage/in_pipeline_layout={\"maxedType\":\"sampler\",\"maxedVisibility\":1,\"extraType\":\"sampler\",\"extraVisibility\":4}","status":"FAIL"},{"name":"webgpu:api/validation/createBindGroupLayout:max_resources_per_stage/in_pipeline_layout={\"maxedType\":\"sampler\",\"maxedVisibility\":1,\"extraType\":\"comparison-sampler\",\"extraVisibility\":1}","status":"FAIL"},{"name":"webgpu:api/validation/createBindGroupLayout:max_resources_per_stage/in_pipeline_layout={\"maxedType\":\"sampler\",\"maxedVisibility\":1,\"extraType\":\"comparison-sampler\",\"extraVisibility\":2}","status":"FAIL"},{"name":"webgpu:api/validation/createBindGroupLayout:max_resources_per_stage/in_pipeline_layout={\"maxedType\":\"sampler\",\"maxedVisibility\":1,\"extraType\":\"comparison-sampler\",\"extraVisibility\":4}","status":"FAIL"},{"name":"webgpu:api/validation/createBindGroupLayout:max_resources_per_stage/in_pipeline_layout={\"maxedType\":\"sampler\",\"maxedVisibility\":1,\"extraType\":\"sampled-texture\",\"extraVisibility\":1}","status":"FAIL"},{"name":"webgpu:api/validation/createBindGroupLayout:max_resources_per_stage/in_pipeline_layout={\"maxedType\":\"sampler\",\"maxedVisibility\":1,\"extraType\":\"sampled-texture\",\"extraVisibility\":2}","status":"FAIL"},{"name":"webgpu:api/validation/createBindGroupLayout:max_resources_per_stage/in_pipeline_layout={\"maxedType\":\"sampler\",\"maxedVisibility\":1,\"extraType\":\"sampled-texture\",\"extraVisibility\":4}","status":"FAIL"},{"name":"webgpu:api/validation/createBindGroupLayout:max_resources_per_stage/in_pipeline_layout={\"maxedType\":\"sampler\",\"maxedVisibility\":2,\"extraType\":\"sampler\",\"extraVisibility\":1}","status":"FAIL"},{"name":"webgpu:api/validation/createBindGroupLayout:max_resources_per_stage/in_pipeline_layout={\"maxedType\":\"sampler\",\"maxedVisibility\":2,\"extraType\":\"sampler\",\"extraVisibility\":2}","status":"FAIL"},{"name":"webgpu:api/validation/createBindGroupLayout:max_resources_per_stage/in_pipeline_layout={\"maxedType\":\"sampler\",\"maxedVisibility\":2,\"extraType\":\"sampler\",\"extraVisibility\":4}","status":"FAIL"},{"name":"webgpu:api/validation/createBindGroupLayout:max_resources_per_stage/in_pipeline_layout={\"maxedType\":\"sampler\",\"maxedVisibility\":2,\"extraType\":\"comparison-sampler\",\"extraVisibility\":1}","status":"FAIL"},{"name":"webgpu:api/validation/createBindGroupLayout:max_resources_per_stage/in_pipeline_layout={\"maxedType\":\"sampler\",\"maxedVisibility\":2,\"extraType\":\"comparison-sampler\",\"extraVisibility\":2}","status":"FAIL"},{"name":"webgpu:api/validation/createBindGroupLayout:max_resources_per_stage/in_pipeline_layout={\"maxedType\":\"sampler\",\"maxedVisibility\":2,\"extraType\":\"comparison-sampler\",\"extraVisibility\":4}","status":"FAIL"},{"name":"webgpu:api/validation/createBindGroupLayout:max_resources_per_stage/in_pipeline_layout={\"maxedType\":\"sampler\",\"maxedVisibility\":2,\"extraType\":\"sampled-texture\",\"extraVisibility\":1}","status":"FAIL"},{"name":"webgpu:api/validation/createBindGroupLayout:max_resources_per_stage/in_pipeline_layout={\"maxedType\":\"sampler\",\"maxedVisibility\":2,\"extraType\":\"sampled-texture\",\"extraVisibility\":2}","status":"FAIL"},{"name":"webgpu:api/validation/createBindGroupLayout:max_resources_per_stage/in_pipeline_layout={\"maxedType\":\"sampler\",\"maxedVisibility\":2,\"extraType\":\"sampled-texture\",\"extraVisibility\":4}","status":"FAIL"},{"name":"webgpu:api/validation/createBindGroupLayout:max_resources_per_stage/in_pipeline_layout={\"maxedType\":\"sampler\",\"maxedVisibility\":4,\"extraType\":\"sampler\",\"extraVisibility\":1}","status":"FAIL"},{"name":"webgpu:api/validation/createBindGroupLayout:max_resources_per_stage/in_pipeline_layout={\"maxedType\":\"sampler\",\"maxedVisibility\":4,\"extraType\":\"sampler\",\"extraVisibility\":2}","status":"FAIL"},{"name":"webgpu:api/validation/createBindGroupLayout:max_resources_per_stage/in_pipeline_layout={\"maxedType\":\"sampler\",\"maxedVisibility\":4,\"extraType\":\"sampler\",\"extraVisibility\":4}","status":"FAIL"},{"name":"webgpu:api/validation/createBindGroupLayout:max_resources_per_stage/in_pipeline_layout={\"maxedType\":\"sampler\",\"maxedVisibility\":4,\"extraType\":\"comparison-sampler\",\"extraVisibility\":1}","status":"FAIL"},{"name":"webgpu:api/validation/createBindGroupLayout:max_resources_per_stage/in_pipeline_layout={\"maxedType\":\"sampler\",\"maxedVisibility\":4,\"extraType\":\"comparison-sampler\",\"extraVisibility\":2}","status":"FAIL"},{"name":"webgpu:api/validation/createBindGroupLayout:max_resources_per_stage/in_pipeline_layout={\"maxedType\":\"sampler\",\"maxedVisibility\":4,\"extraType\":\"comparison-sampler\",\"extraVisibility\":4}","status":"FAIL"},{"name":"webgpu:api/validation/createBindGroupLayout:max_resources_per_stage/in_pipeline_layout={\"maxedType\":\"sampler\",\"maxedVisibility\":4,\"extraType\":\"sampled-texture\",\"extraVisibility\":1}","status":"FAIL"},{"name":"webgpu:api/validation/createBindGroupLayout:max_resources_per_stage/in_pipeline_layout={\"maxedType\":\"sampler\",\"maxedVisibility\":4,\"extraType\":\"sampled-texture\",\"extraVisibility\":2}","status":"FAIL"},{"name":"webgpu:api/validation/createBindGroupLayout:max_resources_per_stage/in_pipeline_layout={\"maxedType\":\"sampler\",\"maxedVisibility\":4,\"extraType\":\"sampled-texture\",\"extraVisibility\":4}","status":"FAIL"},{"name":"webgpu:api/validation/createBindGroupLayout:max_resources_per_stage/in_pipeline_layout={\"maxedType\":\"comparison-sampler\",\"maxedVisibility\":1,\"extraType\":\"sampler\",\"extraVisibility\":1}","status":"FAIL"},{"name":"webgpu:api/validation/createBindGroupLayout:max_resources_per_stage/in_pipeline_layout={\"maxedType\":\"comparison-sampler\",\"maxedVisibility\":1,\"extraType\":\"sampler\",\"extraVisibility\":2}","status":"FAIL"},{"name":"webgpu:api/validation/createBindGroupLayout:max_resources_per_stage/in_pipeline_layout={\"maxedType\":\"comparison-sampler\",\"maxedVisibility\":1,\"extraType\":\"sampler\",\"extraVisibility\":4}","status":"FAIL"},{"name":"webgpu:api/validation/createBindGroupLayout:max_resources_per_stage/in_pipeline_layout={\"maxedType\":\"comparison-sampler\",\"maxedVisibility\":1,\"extraType\":\"comparison-sampler\",\"extraVisibility\":1}","status":"FAIL"},{"name":"webgpu:api/validation/createBindGroupLayout:max_resources_per_stage/in_pipeline_layout={\"maxedType\":\"comparison-sampler\",\"maxedVisibility\":1,\"extraType\":\"comparison-sampler\",\"extraVisibility\":2}","status":"FAIL"},{"name":"webgpu:api/validation/createBindGroupLayout:max_resources_per_stage/in_pipeline_layout={\"maxedType\":\"comparison-sampler\",\"maxedVisibility\":1,\"extraType\":\"comparison-sampler\",\"extraVisibility\":4}","status":"FAIL"},{"name":"webgpu:api/validation/createBindGroupLayout:max_resources_per_stage/in_pipeline_layout={\"maxedType\":\"comparison-sampler\",\"maxedVisibility\":1,\"extraType\":\"sampled-texture\",\"extraVisibility\":1}","status":"FAIL"},{"name":"webgpu:api/validation/createBindGroupLayout:max_resources_per_stage/in_pipeline_layout={\"maxedType\":\"comparison-sampler\",\"maxedVisibility\":1,\"extraType\":\"sampled-texture\",\"extraVisibility\":2}","status":"FAIL"},{"name":"webgpu:api/validation/createBindGroupLayout:max_resources_per_stage/in_pipeline_layout={\"maxedType\":\"comparison-sampler\",\"maxedVisibility\":1,\"extraType\":\"sampled-texture\",\"extraVisibility\":4}","status":"FAIL"},{"name":"webgpu:api/validation/createBindGroupLayout:max_resources_per_stage/in_pipeline_layout={\"maxedType\":\"comparison-sampler\",\"maxedVisibility\":2,\"extraType\":\"sampler\",\"extraVisibility\":1}","status":"FAIL"},{"name":"webgpu:api/validation/createBindGroupLayout:max_resources_per_stage/in_pipeline_layout={\"maxedType\":\"comparison-sampler\",\"maxedVisibility\":2,\"extraType\":\"sampler\",\"extraVisibility\":2}","status":"FAIL"},{"name":"webgpu:api/validation/createBindGroupLayout:max_resources_per_stage/in_pipeline_layout={\"maxedType\":\"comparison-sampler\",\"maxedVisibility\":2,\"extraType\":\"sampler\",\"extraVisibility\":4}","status":"FAIL"},{"name":"webgpu:api/validation/createBindGroupLayout:max_resources_per_stage/in_pipeline_layout={\"maxedType\":\"comparison-sampler\",\"maxedVisibility\":2,\"extraType\":\"comparison-sampler\",\"extraVisibility\":1}","status":"FAIL"},{"name":"webgpu:api/validation/createBindGroupLayout:max_resources_per_stage/in_pipeline_layout={\"maxedType\":\"comparison-sampler\",\"maxedVisibility\":2,\"extraType\":\"comparison-sampler\",\"extraVisibility\":2}","status":"FAIL"},{"name":"webgpu:api/validation/createBindGroupLayout:max_resources_per_stage/in_pipeline_layout={\"maxedType\":\"comparison-sampler\",\"maxedVisibility\":2,\"extraType\":\"comparison-sampler\",\"extraVisibility\":4}","status":"FAIL"},{"name":"webgpu:api/validation/createBindGroupLayout:max_resources_per_stage/in_pipeline_layout={\"maxedType\":\"comparison-sampler\",\"maxedVisibility\":2,\"extraType\":\"sampled-texture\",\"extraVisibility\":1}","status":"FAIL"},{"name":"webgpu:api/validation/createBindGroupLayout:max_resources_per_stage/in_pipeline_layout={\"maxedType\":\"comparison-sampler\",\"maxedVisibility\":2,\"extraType\":\"sampled-texture\",\"extraVisibility\":2}","status":"FAIL"},{"name":"webgpu:api/validation/createBindGroupLayout:max_resources_per_stage/in_pipeline_layout={\"maxedType\":\"comparison-sampler\",\"maxedVisibility\":2,\"extraType\":\"sampled-texture\",\"extraVisibility\":4}","status":"FAIL"},{"name":"webgpu:api/validation/createBindGroupLayout:max_resources_per_stage/in_pipeline_layout={\"maxedType\":\"comparison-sampler\",\"maxedVisibility\":4,\"extraType\":\"sampler\",\"extraVisibility\":1}","status":"FAIL"},{"name":"webgpu:api/validation/createBindGroupLayout:max_resources_per_stage/in_pipeline_layout={\"maxedType\":\"comparison-sampler\",\"maxedVisibility\":4,\"extraType\":\"sampler\",\"extraVisibility\":2}","status":"FAIL"},{"name":"webgpu:api/validation/createBindGroupLayout:max_resources_per_stage/in_pipeline_layout={\"maxedType\":\"comparison-sampler\",\"maxedVisibility\":4,\"extraType\":\"sampler\",\"extraVisibility\":4}","status":"FAIL"},{"name":"webgpu:api/validation/createBindGroupLayout:max_resources_per_stage/in_pipeline_layout={\"maxedType\":\"comparison-sampler\",\"maxedVisibility\":4,\"extraType\":\"comparison-sampler\",\"extraVisibility\":1}","status":"FAIL"},{"name":"webgpu:api/validation/createBindGroupLayout:max_resources_per_stage/in_pipeline_layout={\"maxedType\":\"comparison-sampler\",\"maxedVisibility\":4,\"extraType\":\"comparison-sampler\",\"extraVisibility\":2}","status":"FAIL"},{"name":"webgpu:api/validation/createBindGroupLayout:max_resources_per_stage/in_pipeline_layout={\"maxedType\":\"comparison-sampler\",\"maxedVisibility\":4,\"extraType\":\"comparison-sampler\",\"extraVisibility\":4}","status":"FAIL"},{"name":"webgpu:api/validation/createBindGroupLayout:max_resources_per_stage/in_pipeline_layout={\"maxedType\":\"comparison-sampler\",\"maxedVisibility\":4,\"extraType\":\"sampled-texture\",\"extraVisibility\":1}","status":"FAIL"},{"name":"webgpu:api/validation/createBindGroupLayout:max_resources_per_stage/in_pipeline_layout={\"maxedType\":\"comparison-sampler\",\"maxedVisibility\":4,\"extraType\":\"sampled-texture\",\"extraVisibility\":2}","status":"FAIL"},{"name":"webgpu:api/validation/createBindGroupLayout:max_resources_per_stage/in_pipeline_layout={\"maxedType\":\"comparison-sampler\",\"maxedVisibility\":4,\"extraType\":\"sampled-texture\",\"extraVisibility\":4}","status":"FAIL"},{"name":"webgpu:api/validation/createBindGroupLayout:max_resources_per_stage/in_pipeline_layout={\"maxedType\":\"sampled-texture\",\"maxedVisibility\":1,\"extraType\":\"sampled-texture\",\"extraVisibility\":1}","status":"FAIL"},{"name":"webgpu:api/validation/createBindGroupLayout:max_resources_per_stage/in_pipeline_layout={\"maxedType\":\"sampled-texture\",\"maxedVisibility\":1,\"extraType\":\"sampled-texture\",\"extraVisibility\":2}","status":"FAIL"},{"name":"webgpu:api/validation/createBindGroupLayout:max_resources_per_stage/in_pipeline_layout={\"maxedType\":\"sampled-texture\",\"maxedVisibility\":1,\"extraType\":\"sampled-texture\",\"extraVisibility\":4}","status":"FAIL"},{"name":"webgpu:api/validation/createBindGroupLayout:max_resources_per_stage/in_pipeline_layout={\"maxedType\":\"sampled-texture\",\"maxedVisibility\":1,\"extraType\":\"sampler\",\"extraVisibility\":1}","status":"FAIL"},{"name":"webgpu:api/validation/createBindGroupLayout:max_resources_per_stage/in_pipeline_layout={\"maxedType\":\"sampled-texture\",\"maxedVisibility\":1,\"extraType\":\"sampler\",\"extraVisibility\":2}","status":"FAIL"},{"name":"webgpu:api/validation/createBindGroupLayout:max_resources_per_stage/in_pipeline_layout={\"maxedType\":\"sampled-texture\",\"maxedVisibility\":1,\"extraType\":\"sampler\",\"extraVisibility\":4}","status":"FAIL"},{"name":"webgpu:api/validation/createBindGroupLayout:max_resources_per_stage/in_pipeline_layout={\"maxedType\":\"sampled-texture\",\"maxedVisibility\":2,\"extraType\":\"sampled-texture\",\"extraVisibility\":1}","status":"FAIL"},{"name":"webgpu:api/validation/createBindGroupLayout:max_resources_per_stage/in_pipeline_layout={\"maxedType\":\"sampled-texture\",\"maxedVisibility\":2,\"extraType\":\"sampled-texture\",\"extraVisibility\":2}","status":"FAIL"},{"name":"webgpu:api/validation/createBindGroupLayout:max_resources_per_stage/in_pipeline_layout={\"maxedType\":\"sampled-texture\",\"maxedVisibility\":2,\"extraType\":\"sampled-texture\",\"extraVisibility\":4}","status":"FAIL"},{"name":"webgpu:api/validation/createBindGroupLayout:max_resources_per_stage/in_pipeline_layout={\"maxedType\":\"sampled-texture\",\"maxedVisibility\":2,\"extraType\":\"sampler\",\"extraVisibility\":1}","status":"FAIL"},{"name":"webgpu:api/validation/createBindGroupLayout:max_resources_per_stage/in_pipeline_layout={\"maxedType\":\"sampled-texture\",\"maxedVisibility\":2,\"extraType\":\"sampler\",\"extraVisibility\":2}","status":"FAIL"},{"name":"webgpu:api/validation/createBindGroupLayout:max_resources_per_stage/in_pipeline_layout={\"maxedType\":\"sampled-texture\",\"maxedVisibility\":2,\"extraType\":\"sampler\",\"extraVisibility\":4}","status":"FAIL"},{"name":"webgpu:api/validation/createBindGroupLayout:max_resources_per_stage/in_pipeline_layout={\"maxedType\":\"sampled-texture\",\"maxedVisibility\":4,\"extraType\":\"sampled-texture\",\"extraVisibility\":1}","status":"FAIL"},{"name":"webgpu:api/validation/createBindGroupLayout:max_resources_per_stage/in_pipeline_layout={\"maxedType\":\"sampled-texture\",\"maxedVisibility\":4,\"extraType\":\"sampled-texture\",\"extraVisibility\":2}","status":"FAIL"},{"name":"webgpu:api/validation/createBindGroupLayout:max_resources_per_stage/in_pipeline_layout={\"maxedType\":\"sampled-texture\",\"maxedVisibility\":4,\"extraType\":\"sampled-texture\",\"extraVisibility\":4}","status":"FAIL"},{"name":"webgpu:api/validation/createBindGroupLayout:max_resources_per_stage/in_pipeline_layout={\"maxedType\":\"sampled-texture\",\"maxedVisibility\":4,\"extraType\":\"sampler\",\"extraVisibility\":1}","status":"FAIL"},{"name":"webgpu:api/validation/createBindGroupLayout:max_resources_per_stage/in_pipeline_layout={\"maxedType\":\"sampled-texture\",\"maxedVisibility\":4,\"extraType\":\"sampler\",\"extraVisibility\":2}","status":"FAIL"},{"name":"webgpu:api/validation/createBindGroupLayout:max_resources_per_stage/in_pipeline_layout={\"maxedType\":\"sampled-texture\",\"maxedVisibility\":4,\"extraType\":\"sampler\",\"extraVisibility\":4}","status":"FAIL"},{"name":"webgpu:api/validation/createBindGroupLayout:max_resources_per_stage/in_pipeline_layout={\"maxedType\":\"writeonly-storage-texture\",\"maxedVisibility\":4,\"extraType\":\"writeonly-storage-texture\",\"extraVisibility\":4}","status":"FAIL"},{"name":"webgpu:api/validation/createBindGroupLayout:max_resources_per_stage/in_pipeline_layout={\"maxedType\":\"writeonly-storage-texture\",\"maxedVisibility\":4,\"extraType\":\"readonly-storage-texture\",\"extraVisibility\":1}","status":"FAIL"},{"name":"webgpu:api/validation/createBindGroupLayout:max_resources_per_stage/in_pipeline_layout={\"maxedType\":\"writeonly-storage-texture\",\"maxedVisibility\":4,\"extraType\":\"readonly-storage-texture\",\"extraVisibility\":2}","status":"FAIL"},{"name":"webgpu:api/validation/createBindGroupLayout:max_resources_per_stage/in_pipeline_layout={\"maxedType\":\"writeonly-storage-texture\",\"maxedVisibility\":4,\"extraType\":\"readonly-storage-texture\",\"extraVisibility\":4}","status":"FAIL"},{"name":"webgpu:api/validation/createBindGroupLayout:max_resources_per_stage/in_pipeline_layout={\"maxedType\":\"writeonly-storage-texture\",\"maxedVisibility\":4,\"extraType\":\"sampler\",\"extraVisibility\":1}","status":"FAIL"},{"name":"webgpu:api/validation/createBindGroupLayout:max_resources_per_stage/in_pipeline_layout={\"maxedType\":\"writeonly-storage-texture\",\"maxedVisibility\":4,\"extraType\":\"sampler\",\"extraVisibility\":2}","status":"FAIL"},{"name":"webgpu:api/validation/createBindGroupLayout:max_resources_per_stage/in_pipeline_layout={\"maxedType\":\"writeonly-storage-texture\",\"maxedVisibility\":4,\"extraType\":\"sampler\",\"extraVisibility\":4}","status":"FAIL"},{"name":"webgpu:api/validation/createBindGroupLayout:max_resources_per_stage/in_pipeline_layout={\"maxedType\":\"readonly-storage-texture\",\"maxedVisibility\":1,\"extraType\":\"writeonly-storage-texture\",\"extraVisibility\":4}","status":"FAIL"},{"name":"webgpu:api/validation/createBindGroupLayout:max_resources_per_stage/in_pipeline_layout={\"maxedType\":\"readonly-storage-texture\",\"maxedVisibility\":1,\"extraType\":\"readonly-storage-texture\",\"extraVisibility\":1}","status":"FAIL"},{"name":"webgpu:api/validation/createBindGroupLayout:max_resources_per_stage/in_pipeline_layout={\"maxedType\":\"readonly-storage-texture\",\"maxedVisibility\":1,\"extraType\":\"readonly-storage-texture\",\"extraVisibility\":2}","status":"FAIL"},{"name":"webgpu:api/validation/createBindGroupLayout:max_resources_per_stage/in_pipeline_layout={\"maxedType\":\"readonly-storage-texture\",\"maxedVisibility\":1,\"extraType\":\"readonly-storage-texture\",\"extraVisibility\":4}","status":"FAIL"},{"name":"webgpu:api/validation/createBindGroupLayout:max_resources_per_stage/in_pipeline_layout={\"maxedType\":\"readonly-storage-texture\",\"maxedVisibility\":1,\"extraType\":\"sampler\",\"extraVisibility\":1}","status":"FAIL"},{"name":"webgpu:api/validation/createBindGroupLayout:max_resources_per_stage/in_pipeline_layout={\"maxedType\":\"readonly-storage-texture\",\"maxedVisibility\":1,\"extraType\":\"sampler\",\"extraVisibility\":2}","status":"FAIL"},{"name":"webgpu:api/validation/createBindGroupLayout:max_resources_per_stage/in_pipeline_layout={\"maxedType\":\"readonly-storage-texture\",\"maxedVisibility\":1,\"extraType\":\"sampler\",\"extraVisibility\":4}","status":"FAIL"},{"name":"webgpu:api/validation/createBindGroupLayout:max_resources_per_stage/in_pipeline_layout={\"maxedType\":\"readonly-storage-texture\",\"maxedVisibility\":2,\"extraType\":\"writeonly-storage-texture\",\"extraVisibility\":4}","status":"FAIL"},{"name":"webgpu:api/validation/createBindGroupLayout:max_resources_per_stage/in_pipeline_layout={\"maxedType\":\"readonly-storage-texture\",\"maxedVisibility\":2,\"extraType\":\"readonly-storage-texture\",\"extraVisibility\":1}","status":"FAIL"},{"name":"webgpu:api/validation/createBindGroupLayout:max_resources_per_stage/in_pipeline_layout={\"maxedType\":\"readonly-storage-texture\",\"maxedVisibility\":2,\"extraType\":\"readonly-storage-texture\",\"extraVisibility\":2}","status":"FAIL"},{"name":"webgpu:api/validation/createBindGroupLayout:max_resources_per_stage/in_pipeline_layout={\"maxedType\":\"readonly-storage-texture\",\"maxedVisibility\":2,\"extraType\":\"readonly-storage-texture\",\"extraVisibility\":4}","status":"FAIL"},{"name":"webgpu:api/validation/createBindGroupLayout:max_resources_per_stage/in_pipeline_layout={\"maxedType\":\"readonly-storage-texture\",\"maxedVisibility\":2,\"extraType\":\"sampler\",\"extraVisibility\":1}","status":"FAIL"},{"name":"webgpu:api/validation/createBindGroupLayout:max_resources_per_stage/in_pipeline_layout={\"maxedType\":\"readonly-storage-texture\",\"maxedVisibility\":2,\"extraType\":\"sampler\",\"extraVisibility\":2}","status":"FAIL"},{"name":"webgpu:api/validation/createBindGroupLayout:max_resources_per_stage/in_pipeline_layout={\"maxedType\":\"readonly-storage-texture\",\"maxedVisibility\":2,\"extraType\":\"sampler\",\"extraVisibility\":4}","status":"FAIL"},{"name":"webgpu:api/validation/createBindGroupLayout:max_resources_per_stage/in_pipeline_layout={\"maxedType\":\"readonly-storage-texture\",\"maxedVisibility\":4,\"extraType\":\"writeonly-storage-texture\",\"extraVisibility\":4}","status":"FAIL"},{"name":"webgpu:api/validation/createBindGroupLayout:max_resources_per_stage/in_pipeline_layout={\"maxedType\":\"readonly-storage-texture\",\"maxedVisibility\":4,\"extraType\":\"readonly-storage-texture\",\"extraVisibility\":1}","status":"FAIL"},{"name":"webgpu:api/validation/createBindGroupLayout:max_resources_per_stage/in_pipeline_layout={\"maxedType\":\"readonly-storage-texture\",\"maxedVisibility\":4,\"extraType\":\"readonly-storage-texture\",\"extraVisibility\":2}","status":"FAIL"},{"name":"webgpu:api/validation/createBindGroupLayout:max_resources_per_stage/in_pipeline_layout={\"maxedType\":\"readonly-storage-texture\",\"maxedVisibility\":4,\"extraType\":\"readonly-storage-texture\",\"extraVisibility\":4}","status":"FAIL"},{"name":"webgpu:api/validation/createBindGroupLayout:max_resources_per_stage/in_pipeline_layout={\"maxedType\":\"readonly-storage-texture\",\"maxedVisibility\":4,\"extraType\":\"sampler\",\"extraVisibility\":1}","status":"FAIL"},{"name":"webgpu:api/validation/createBindGroupLayout:max_resources_per_stage/in_pipeline_layout={\"maxedType\":\"readonly-storage-texture\",\"maxedVisibility\":4,\"extraType\":\"sampler\",\"extraVisibility\":2}","status":"FAIL"},{"name":"webgpu:api/validation/createBindGroupLayout:max_resources_per_stage/in_pipeline_layout={\"maxedType\":\"readonly-storage-texture\",\"maxedVisibility\":4,\"extraType\":\"sampler\",\"extraVisibility\":4}","status":"FAIL"}]}