{"status":"OK","subtests":[{"name":"The template contents must be a DocumentFragment (empty template)","status":"PASS"},{"name":"The template contents must be a DocumentFragment (non empty template)","status":"PASS"},{"name":"The template contents must be a DocumentFragment (non empty template containing div which is an Element instance)","status":"PASS"},{"name":"The template contents must be a DocumentFragment (not empty template containing text node)","status":"PASS"},{"name":"The template contents must be a DocumentFragment (nested template containing a text node)","status":"PASS"},{"name":"The template contents must be a DocumentFragment (the empty template tag inside HTML file loaded in iframe)","status":"PASS"},{"name":"The template contents must be a DocumentFragment (non empty template tag inside HTML file loaded in iframe)","status":"PASS"},{"name":"The template contents must be a DocumentFragment (the template tag with some text inside HTML file loaded in iframe)","status":"PASS"},{"name":"The template contents must be a DocumentFragment (the template tag with nested template tag inside HTML file loaded in iframe)","status":"PASS"}]}