{"status":"OK","subtests":[{"name":"# AUDIT TASK RUNNER STARTED.","status":"PASS"},{"name":"> [synthesize-verify] ","status":"PASS"},{"name":"  The zero playbackRate held the sample value correctly","status":"PASS"},{"name":"< [synthesize-verify] All assertions passed. (total 1 assertions)","status":"PASS"},{"name":"> [subsample start with playback rate 0] ","status":"PASS"},{"name":"  output[0:27] contains only the constant 0.","status":"PASS"},{"name":"  output[28:] contains only the constant 5.","status":"PASS"},{"name":"< [subsample start with playback rate 0] All assertions passed. (total 2 assertions)","status":"PASS"},{"name":"# AUDIT TASK RUNNER FINISHED: 2 tasks ran successfully.","status":"PASS"}]}